{"config": {"view": {"continuousWidth": 400, "continuousHeight": 300}}, "layer": [{"data": {"name": "data-c1b12bb051394a382f086421c4ad04d7"}, "mark": "line", "encoding": {"x": {"type": "quantitative", "field": "policy_years"}, "y": {"type": "quantitative", "field": "MME_per_cap"}}, "title": "Pre-Post Policy: Florida, Opioids per cap", "transform": [{"on": "policy_years", "regression": "MME_per_cap"}]}, {"layer": [{"mark": "errorband", "encoding": {"x": {"type": "quantitative", "field": "policy_years"}, "y": {"type": "quantitative", "field": "ci_low", "title": "MME_per_cap"}, "y2": {"field": "ci_high"}}}, {"mark": "line", "encoding": {"x": {"type": "quantitative", "field": "policy_years"}, "y": {"type": "quantitative", "field": "MME_per_cap"}}}], "data": {"name": "data-113aab7bb94a80666f0f75e4829506a2"}}, {"layer": [{"mark": "errorband", "encoding": {"x": {"type": "quantitative", "field": "policy_years"}, "y": {"type": "quantitative", "field": "ci_low", "title": "MME_per_cap"}, "y2": {"field": "ci_high"}}}, {"mark": "line", "encoding": {"x": {"type": "quantitative", "field": "policy_years"}, "y": {"type": "quantitative", "field": "MME_per_cap"}}}], "data": {"name": "data-c67d166d1bf8cb5a927f377e0e32ec7e"}}, {"data": {"name": "data-1cf7c250840e3c595c11ebf7ebbb5cbe"}, "mark": {"type": "rule", "color": "black", "strokeDash": [10, 10]}, "encoding": {"x": {"type": "quantitative", "field": "a"}}}], "$schema": "https://vega.github.io/schema/vega-lite/v4.8.1.json", "datasets": {"data-c1b12bb051394a382f086421c4ad04d7": [{"BUYER_STATE": "FL", "BUYER_COUNTY": "ALACHUA", "fips": "12001", "year": 2006, "MME": 82596618.68772501, "Population": 239506.0, "MME_per_cap": 344.86241967936087, "treatment": 1, "policy_years": -4}, {"BUYER_STATE": "FL", "BUYER_COUNTY": "ALACHUA", "fips": "12001", "year": 2007, "MME": 95259627.97678751, "Population": 242685.0, "MME_per_cap": 392.5237570380844, "treatment": 1, "policy_years": -3}, {"BUYER_STATE": "FL", "BUYER_COUNTY": "ALACHUA", "fips": "12001", "year": 2008, "MME": 114675221.9217625, "Population": 244888.0, "MME_per_cap": 468.27619941263964, "treatment": 1, "policy_years": -2}, {"BUYER_STATE": "FL", "BUYER_COUNTY": "ALACHUA", "fips": "12001", "year": 2009, "MME": 141281048.185425, "Population": 246657.0, "MME_per_cap": 572.7834530762354, "treatment": 1, "policy_years": -1}, {"BUYER_STATE": "FL", "BUYER_COUNTY": "BAKER", "fips": "12003", "year": 2006, "MME": 11900178.637500001, "Population": 25571.0, "MME_per_cap": 465.37791394548515, "treatment": 1, "policy_years": -4}, {"BUYER_STATE": "FL", "BUYER_COUNTY": "BAKER", "fips": "12003", "year": 2007, "MME": 13793788.183225, "Population": 26212.0, "MME_per_cap": 526.2394393111933, "treatment": 1, "policy_years": -3}, {"BUYER_STATE": "FL", "BUYER_COUNTY": "BAKER", "fips": "12003", "year": 2008, "MME": 15651322.154225001, "Population": 26725.0, "MME_per_cap": 585.6434856585595, "treatment": 1, "policy_years": -2}, {"BUYER_STATE": "FL", "BUYER_COUNTY": "BAKER", "fips": "12003", "year": 2009, "MME": 19165967.295, "Population": 27124.0, "MME_per_cap": 706.6054894189648, "treatment": 1, "policy_years": -1}, {"BUYER_STATE": "FL", "BUYER_COUNTY": "BAY", "fips": "12005", "year": 2006, "MME": 61998102.472075, "Population": 165644.0, "MME_per_cap": 374.28522899757917, "treatment": 1, "policy_years": -4}, {"BUYER_STATE": "FL", "BUYER_COUNTY": "BAY", "fips": "12005", "year": 2007, "MME": 61255857.999262504, "Population": 165345.0, "MME_per_cap": 370.472998876667, "treatment": 1, "policy_years": -3}, {"BUYER_STATE": "FL", "BUYER_COUNTY": "BAY", "fips": "12005", "year": 2008, "MME": 65665012.9212625, "Population": 166267.0, "MME_per_cap": 394.93713678157724, "treatment": 1, "policy_years": -2}, {"BUYER_STATE": "FL", "BUYER_COUNTY": "BAY", "fips": "12005", "year": 2009, "MME": 68131167.19293751, "Population": 167464.0, "MME_per_cap": 406.8406773571485, "treatment": 1, "policy_years": -1}, {"BUYER_STATE": "FL", "BUYER_COUNTY": "BRADFORD", "fips": "12007", "year": 2006, "MME": 13424830.8949, "Population": 28506.0, "MME_per_cap": 470.94755121377955, "treatment": 1, "policy_years": -4}, {"BUYER_STATE": "FL", "BUYER_COUNTY": "BRADFORD", "fips": "12007", "year": 2007, "MME": 15854865.475125, "Population": 28825.0, "MME_per_cap": 550.0386981830009, "treatment": 1, "policy_years": -3}, {"BUYER_STATE": "FL", "BUYER_COUNTY": "BRADFORD", "fips": "12007", "year": 2008, "MME": 17501063.6835, "Population": 28961.0, "MME_per_cap": 604.2976307275301, "treatment": 1, "policy_years": -2}, {"BUYER_STATE": "FL", "BUYER_COUNTY": "BRADFORD", "fips": "12007", "year": 2009, "MME": 21250949.6668125, "Population": 28979.0, "MME_per_cap": 733.3223943825702, "treatment": 1, "policy_years": -1}, {"BUYER_STATE": "FL", "BUYER_COUNTY": "BREVARD", "fips": "12009", "year": 2006, "MME": 201186153.403075, "Population": 535138.0, "MME_per_cap": 375.95191035410494, "treatment": 1, "policy_years": -4}, {"BUYER_STATE": "FL", "BUYER_COUNTY": "BREVARD", "fips": "12009", "year": 2007, "MME": 246505683.9382375, "Population": 539719.0, "MME_per_cap": 456.7296758836311, "treatment": 1, "policy_years": -3}, {"BUYER_STATE": "FL", "BUYER_COUNTY": "BREVARD", "fips": "12009", "year": 2008, "MME": 317947599.2637875, "Population": 542378.0, "MME_per_cap": 586.2103537823943, "treatment": 1, "policy_years": -2}, {"BUYER_STATE": "FL", "BUYER_COUNTY": "BREVARD", "fips": "12009", "year": 2009, "MME": 365366249.71935, "Population": 542109.0, "MME_per_cap": 673.9719313262646, "treatment": 1, "policy_years": -1}, {"BUYER_STATE": "FL", "BUYER_COUNTY": "BROWARD", "fips": "12011", "year": 2006, "MME": 1222607389.6560626, "Population": 1739348.0, "MME_per_cap": 702.9113148467487, "treatment": 1, "policy_years": -4}, {"BUYER_STATE": "FL", "BUYER_COUNTY": "BROWARD", "fips": "12011", "year": 2007, "MME": 1720337481.7214875, "Population": 1720825.0, "MME_per_cap": 999.716695027959, "treatment": 1, "policy_years": -3}, {"BUYER_STATE": "FL", "BUYER_COUNTY": "BROWARD", "fips": "12011", "year": 2008, "MME": 2180537488.6392627, "Population": 1723633.0, "MME_per_cap": 1265.0822353942299, "treatment": 1, "policy_years": -2}, {"BUYER_STATE": "FL", "BUYER_COUNTY": "BROWARD", "fips": "12011", "year": 2009, "MME": 2584508114.0166197, "Population": 1733310.0, "MME_per_cap": 1491.0824457348194, "treatment": 1, "policy_years": -1}, {"BUYER_STATE": "FL", "BUYER_COUNTY": "CALHOUN", "fips": "12013", "year": 2006, "MME": 1851905.823, "Population": 13997.0, "MME_per_cap": 132.30733892977068, "treatment": 1, "policy_years": -4}, {"BUYER_STATE": "FL", "BUYER_COUNTY": "CALHOUN", "fips": "12013", "year": 2007, "MME": 2021532.2535, "Population": 14222.0, "MME_per_cap": 142.14120753058643, "treatment": 1, "policy_years": -3}, {"BUYER_STATE": "FL", "BUYER_COUNTY": "CALHOUN", "fips": "12013", "year": 2008, "MME": 2225156.55, "Population": 14351.0, "MME_per_cap": 155.05236917287993, "treatment": 1, "policy_years": -2}, {"BUYER_STATE": "FL", "BUYER_COUNTY": "CALHOUN", "fips": "12013", "year": 2009, "MME": 2580235.47, "Population": 14692.0, "MME_per_cap": 175.62179893819768, "treatment": 1, "policy_years": -1}, {"BUYER_STATE": "FL", "BUYER_COUNTY": "CHARLOTTE", "fips": "12015", "year": 2006, "MME": 82123597.1579375, "Population": 157099.0, "MME_per_cap": 522.7506041282089, "treatment": 1, "policy_years": -4}, {"BUYER_STATE": "FL", "BUYER_COUNTY": "CHARLOTTE", "fips": "12015", "year": 2007, "MME": 103366666.8672, "Population": 159742.0, "MME_per_cap": 647.0850926318689, "treatment": 1, "policy_years": -3}, {"BUYER_STATE": "FL", "BUYER_COUNTY": "CHARLOTTE", "fips": "12015", "year": 2008, "MME": 142308398.400525, "Population": 160467.0, "MME_per_cap": 886.8390285885883, "treatment": 1, "policy_years": -2}, {"BUYER_STATE": "FL", "BUYER_COUNTY": "CHARLOTTE", "fips": "12015", "year": 2009, "MME": 191565348.6274875, "Population": 159629.0, "MME_per_cap": 1200.0660821497818, "treatment": 1, "policy_years": -1}, {"BUYER_STATE": "FL", "BUYER_COUNTY": "CITRUS", "fips": "12017", "year": 2006, "MME": 49646891.0293375, "Population": 137826.0, "MME_per_cap": 360.2142631240659, "treatment": 1, "policy_years": -4}, {"BUYER_STATE": "FL", "BUYER_COUNTY": "CITRUS", "fips": "12017", "year": 2007, "MME": 58420509.5731125, "Population": 140974.0, "MME_per_cap": 414.40627046911135, "treatment": 1, "policy_years": -3}, {"BUYER_STATE": "FL", "BUYER_COUNTY": "CITRUS", "fips": "12017", "year": 2008, "MME": 71761417.6846625, "Population": 142122.0, "MME_per_cap": 504.9282847459402, "treatment": 1, "policy_years": -2}, {"BUYER_STATE": "FL", "BUYER_COUNTY": "CITRUS", "fips": "12017", "year": 2009, "MME": 81649551.25245, "Population": 141381.0, "MME_per_cap": 577.5143141755258, "treatment": 1, "policy_years": -1}, {"BUYER_STATE": "FL", "BUYER_COUNTY": "CLAY", "fips": "12019", "year": 2006, "MME": 69327289.9772, "Population": 178339.0, "MME_per_cap": 388.73880630260345, "treatment": 1, "policy_years": -4}, {"BUYER_STATE": "FL", "BUYER_COUNTY": "CLAY", "fips": "12019", "year": 2007, "MME": 85815940.69482501, "Population": 184256.0, "MME_per_cap": 465.74299178764875, "treatment": 1, "policy_years": -3}, {"BUYER_STATE": "FL", "BUYER_COUNTY": "CLAY", "fips": "12019", "year": 2008, "MME": 98532925.9160125, "Population": 187289.0, "MME_per_cap": 526.1009771850589, "treatment": 1, "policy_years": -2}, {"BUYER_STATE": "FL", "BUYER_COUNTY": "CLAY", "fips": "12019", "year": 2009, "MME": 125011367.1661125, "Population": 189101.0, "MME_per_cap": 661.0825282050994, "treatment": 1, "policy_years": -1}, {"BUYER_STATE": "FL", "BUYER_COUNTY": "COLLIER", "fips": "12021", "year": 2006, "MME": 107528680.73415, "Population": 312621.0, "MME_per_cap": 343.95859758029695, "treatment": 1, "policy_years": -4}, {"BUYER_STATE": "FL", "BUYER_COUNTY": "COLLIER", "fips": "12021", "year": 2007, "MME": 129910312.756925, "Population": 314437.0, "MME_per_cap": 413.1521187294275, "treatment": 1, "policy_years": -3}, {"BUYER_STATE": "FL", "BUYER_COUNTY": "COLLIER", "fips": "12021", "year": 2008, "MME": 147472347.386, "Population": 316641.0, "MME_per_cap": 465.73989908445213, "treatment": 1, "policy_years": -2}, {"BUYER_STATE": "FL", "BUYER_COUNTY": "COLLIER", "fips": "12021", "year": 2009, "MME": 202995696.267675, "Population": 318485.0, "MME_per_cap": 637.379142715277, "treatment": 1, "policy_years": -1}, {"BUYER_STATE": "FL", "BUYER_COUNTY": "COLUMBIA", "fips": "12023", "year": 2006, "MME": 27550681.7085875, "Population": 65890.0, "MME_per_cap": 418.13145710407497, "treatment": 1, "policy_years": -4}, {"BUYER_STATE": "FL", "BUYER_COUNTY": "COLUMBIA", "fips": "12023", "year": 2007, "MME": 30011436.1680125, "Population": 66604.0, "MME_per_cap": 450.59510191598855, "treatment": 1, "policy_years": -3}, {"BUYER_STATE": "FL", "BUYER_COUNTY": "COLUMBIA", "fips": "12023", "year": 2008, "MME": 37731017.1378125, "Population": 67318.0, "MME_per_cap": 560.4892768325337, "treatment": 1, "policy_years": -2}, {"BUYER_STATE": "FL", "BUYER_COUNTY": "COLUMBIA", "fips": "12023", "year": 2009, "MME": 40150096.770225, "Population": 67412.0, "MME_per_cap": 595.5927248891147, "treatment": 1, "policy_years": -1}, {"BUYER_STATE": "FL", "BUYER_COUNTY": "DESOTO", "fips": "12027", "year": 2006, "MME": 7179580.0115, "Population": 34300.0, "MME_per_cap": 209.31720150145773, "treatment": 1, "policy_years": -4}, {"BUYER_STATE": "FL", "BUYER_COUNTY": "DESOTO", "fips": "12027", "year": 2007, "MME": 7726090.7717925, "Population": 34537.0, "MME_per_cap": 223.7047448183832, "treatment": 1, "policy_years": -3}, {"BUYER_STATE": "FL", "BUYER_COUNTY": "DESOTO", "fips": "12027", "year": 2008, "MME": 7953604.365, "Population": 34374.0, "MME_per_cap": 231.38431270727875, "treatment": 1, "policy_years": -2}, {"BUYER_STATE": "FL", "BUYER_COUNTY": "DESOTO", "fips": "12027", "year": 2009, "MME": 9826920.24, "Population": 34592.0, "MME_per_cap": 284.0807192414431, "treatment": 1, "policy_years": -1}, {"BUYER_STATE": "FL", "BUYER_COUNTY": "DIXIE", "fips": "12029", "year": 2006, "MME": 2952746.125, "Population": 15892.0, "MME_per_cap": 185.80078813239365, "treatment": 1, "policy_years": -4}, {"BUYER_STATE": "FL", "BUYER_COUNTY": "DIXIE", "fips": "12029", "year": 2007, "MME": 3098699.7413625, "Population": 16083.0, "MME_per_cap": 192.6692620383324, "treatment": 1, "policy_years": -3}, {"BUYER_STATE": "FL", "BUYER_COUNTY": "DIXIE", "fips": "12029", "year": 2008, "MME": 3247389.765, "Population": 16214.0, "MME_per_cap": 200.28307419514002, "treatment": 1, "policy_years": -2}, {"BUYER_STATE": "FL", "BUYER_COUNTY": "DIXIE", "fips": "12029", "year": 2009, "MME": 2874669.0413625, "Population": 16403.0, "MME_per_cap": 175.25263923443882, "treatment": 1, "policy_years": -1}, {"BUYER_STATE": "FL", "BUYER_COUNTY": "DUVAL", "fips": "12031", "year": 2006, "MME": 293452975.4726625, "Population": 842098.0, "MME_per_cap": 348.4784140001075, "treatment": 1, "policy_years": -4}, {"BUYER_STATE": "FL", "BUYER_COUNTY": "DUVAL", "fips": "12031", "year": 2007, "MME": 344954365.4414875, "Population": 851033.0, "MME_per_cap": 405.33606269261884, "treatment": 1, "policy_years": -3}, {"BUYER_STATE": "FL", "BUYER_COUNTY": "DUVAL", "fips": "12031", "year": 2008, "MME": 408809255.0861, "Population": 855437.0, "MME_per_cap": 477.8952220749161, "treatment": 1, "policy_years": -2}, {"BUYER_STATE": "FL", "BUYER_COUNTY": "DUVAL", "fips": "12031", "year": 2009, "MME": 534398118.6508125, "Population": 859795.0, "MME_per_cap": 621.5413193270634, "treatment": 1, "policy_years": -1}, {"BUYER_STATE": "FL", "BUYER_COUNTY": "ESCAMBIA", "fips": "12033", "year": 2006, "MME": 96186447.3270125, "Population": 300395.0, "MME_per_cap": 320.1998945622014, "treatment": 1, "policy_years": -4}, {"BUYER_STATE": "FL", "BUYER_COUNTY": "ESCAMBIA", "fips": "12033", "year": 2007, "MME": 113832921.20252751, "Population": 297393.0, "MME_per_cap": 382.76933620672816, "treatment": 1, "policy_years": -3}, {"BUYER_STATE": "FL", "BUYER_COUNTY": "ESCAMBIA", "fips": "12033", "year": 2008, "MME": 116136843.9933875, "Population": 296854.0, "MME_per_cap": 391.2254643474149, "treatment": 1, "policy_years": -2}, {"BUYER_STATE": "FL", "BUYER_COUNTY": "ESCAMBIA", "fips": "12033", "year": 2009, "MME": 127790391.844725, "Population": 297015.0, "MME_per_cap": 430.2489498669259, "treatment": 1, "policy_years": -1}, {"BUYER_STATE": "FL", "BUYER_COUNTY": "FLAGLER", "fips": "12035", "year": 2006, "MME": 21015019.383675, "Population": 84339.0, "MME_per_cap": 249.1732103021734, "treatment": 1, "policy_years": -4}, {"BUYER_STATE": "FL", "BUYER_COUNTY": "FLAGLER", "fips": "12035", "year": 2007, "MME": 24313087.5877625, "Population": 90516.0, "MME_per_cap": 268.6054132723773, "treatment": 1, "policy_years": -3}, {"BUYER_STATE": "FL", "BUYER_COUNTY": "FLAGLER", "fips": "12035", "year": 2008, "MME": 30727470.41245, "Population": 93546.0, "MME_per_cap": 328.4744447913326, "treatment": 1, "policy_years": -2}, {"BUYER_STATE": "FL", "BUYER_COUNTY": "FLAGLER", "fips": "12035", "year": 2009, "MME": 45094206.1172625, "Population": 94700.0, "MME_per_cap": 476.1795788517687, "treatment": 1, "policy_years": -1}, {"BUYER_STATE": "FL", "BUYER_COUNTY": "FRANKLIN", "fips": "12037", "year": 2006, "MME": 2174577.223, "Population": 11308.0, "MME_per_cap": 192.30431756278742, "treatment": 1, "policy_years": -4}, {"BUYER_STATE": "FL", "BUYER_COUNTY": "FRANKLIN", "fips": "12037", "year": 2007, "MME": 2099076.5175, "Population": 11491.0, "MME_per_cap": 182.67135301540335, "treatment": 1, "policy_years": -3}, {"BUYER_STATE": "FL", "BUYER_COUNTY": "FRANKLIN", "fips": "12037", "year": 2008, "MME": 2152977.9473625002, "Population": 11484.0, "MME_per_cap": 187.4763102893156, "treatment": 1, "policy_years": -2}, {"BUYER_STATE": "FL", "BUYER_COUNTY": "FRANKLIN", "fips": "12037", "year": 2009, "MME": 1955352.12, "Population": 11515.0, "MME_per_cap": 169.80912896222318, "treatment": 1, "policy_years": -1}, {"BUYER_STATE": "FL", "BUYER_COUNTY": "GADSDEN", "fips": "12039", "year": 2006, "MME": 6021017.100225001, "Population": 45258.0, "MME_per_cap": 133.03763092105265, "treatment": 1, "policy_years": -4}, {"BUYER_STATE": "FL", "BUYER_COUNTY": "GADSDEN", "fips": "12039", "year": 2007, "MME": 7138511.4675, "Population": 45867.0, "MME_per_cap": 155.63502011249918, "treatment": 1, "policy_years": -3}, {"BUYER_STATE": "FL", "BUYER_COUNTY": "GADSDEN", "fips": "12039", "year": 2008, "MME": 6724820.623500001, "Population": 46319.0, "MME_per_cap": 145.18492677950735, "treatment": 1, "policy_years": -2}, {"BUYER_STATE": "FL", "BUYER_COUNTY": "GADSDEN", "fips": "12039", "year": 2009, "MME": 7168381.8568125, "Population": 46264.0, "MME_per_cap": 154.9451378353039, "treatment": 1, "policy_years": -1}, {"BUYER_STATE": "FL", "BUYER_COUNTY": "GILCHRIST", "fips": "12041", "year": 2006, "MME": 4032605.95, "Population": 16223.0, "MME_per_cap": 248.57338038587193, "treatment": 1, "policy_years": -4}, {"BUYER_STATE": "FL", "BUYER_COUNTY": "GILCHRIST", "fips": "12041", "year": 2007, "MME": 4195956.2895, "Population": 16610.0, "MME_per_cap": 252.6162726971704, "treatment": 1, "policy_years": -3}, {"BUYER_STATE": "FL", "BUYER_COUNTY": "GILCHRIST", "fips": "12041", "year": 2008, "MME": 4955842.2, "Population": 16797.0, "MME_per_cap": 295.0432934452581, "treatment": 1, "policy_years": -2}, {"BUYER_STATE": "FL", "BUYER_COUNTY": "GILCHRIST", "fips": "12041", "year": 2009, "MME": 6117871.9913625, "Population": 16829.0, "MME_per_cap": 363.5315224530572, "treatment": 1, "policy_years": -1}, {"BUYER_STATE": "FL", "BUYER_COUNTY": "GLADES", "fips": "12043", "year": 2009, "MME": 2627311.2, "Population": 12839.0, "MME_per_cap": 204.6351896565153, "treatment": 1, "policy_years": -1}, {"BUYER_STATE": "FL", "BUYER_COUNTY": "GULF", "fips": "12045", "year": 2006, "MME": 3543341.616, "Population": 15856.0, "MME_per_cap": 223.47008173562057, "treatment": 1, "policy_years": -4}, {"BUYER_STATE": "FL", "BUYER_COUNTY": "GULF", "fips": "12045", "year": 2007, "MME": 3813947.766, "Population": 15908.0, "MME_per_cap": 239.75029959768668, "treatment": 1, "policy_years": -3}, {"BUYER_STATE": "FL", "BUYER_COUNTY": "GULF", "fips": "12045", "year": 2008, "MME": 3573714.215, "Population": 15851.0, "MME_per_cap": 225.45670399343888, "treatment": 1, "policy_years": -2}, {"BUYER_STATE": "FL", "BUYER_COUNTY": "GULF", "fips": "12045", "year": 2009, "MME": 3494621.7075, "Population": 15933.0, "MME_per_cap": 219.33231077009978, "treatment": 1, "policy_years": -1}, {"BUYER_STATE": "FL", "BUYER_COUNTY": "HAMILTON", "fips": "12047", "year": 2006, "MME": 1804899.5505000001, "Population": 14430.0, "MME_per_cap": 125.07966392931394, "treatment": 1, "policy_years": -4}, {"BUYER_STATE": "FL", "BUYER_COUNTY": "HAMILTON", "fips": "12047", "year": 2007, "MME": 2249353.0935, "Population": 14589.0, "MME_per_cap": 154.18144447871683, "treatment": 1, "policy_years": -3}, {"BUYER_STATE": "FL", "BUYER_COUNTY": "HAMILTON", "fips": "12047", "year": 2008, "MME": 3039991.791, "Population": 14785.0, "MME_per_cap": 205.61324254311805, "treatment": 1, "policy_years": -2}, {"BUYER_STATE": "FL", "BUYER_COUNTY": "HAMILTON", "fips": "12047", "year": 2009, "MME": 2305155.3525, "Population": 14930.0, "MME_per_cap": 154.39754537843268, "treatment": 1, "policy_years": -1}, {"BUYER_STATE": "FL", "BUYER_COUNTY": "HARDEE", "fips": "12049", "year": 2006, "MME": 3682568.105, "Population": 27049.0, "MME_per_cap": 136.14433454101814, "treatment": 1, "policy_years": -4}, {"BUYER_STATE": "FL", "BUYER_COUNTY": "HARDEE", "fips": "12049", "year": 2007, "MME": 3996159.5725000002, "Population": 27489.0, "MME_per_cap": 145.37304276255958, "treatment": 1, "policy_years": -3}, {"BUYER_STATE": "FL", "BUYER_COUNTY": "HARDEE", "fips": "12049", "year": 2008, "MME": 4647926.0445, "Population": 27603.0, "MME_per_cap": 168.38481485708076, "treatment": 1, "policy_years": -2}, {"BUYER_STATE": "FL", "BUYER_COUNTY": "HARDEE", "fips": "12049", "year": 2009, "MME": 7751621.3925, "Population": 27661.0, "MME_per_cap": 280.23648431003943, "treatment": 1, "policy_years": -1}, {"BUYER_STATE": "FL", "BUYER_COUNTY": "HENDRY", "fips": "12051", "year": 2006, "MME": 16527160.2825, "Population": 38776.0, "MME_per_cap": 426.2213813312358, "treatment": 1, "policy_years": -4}, {"BUYER_STATE": "FL", "BUYER_COUNTY": "HENDRY", "fips": "12051", "year": 2007, "MME": 19191329.0120875, "Population": 39006.0, "MME_per_cap": 492.00966548960423, "treatment": 1, "policy_years": -3}, {"BUYER_STATE": "FL", "BUYER_COUNTY": "HENDRY", "fips": "12051", "year": 2008, "MME": 20998036.911, "Population": 39177.0, "MME_per_cap": 535.9786842024657, "treatment": 1, "policy_years": -2}, {"BUYER_STATE": "FL", "BUYER_COUNTY": "HENDRY", "fips": "12051", "year": 2009, "MME": 22472576.881575, "Population": 39010.0, "MME_per_cap": 576.0722092175083, "treatment": 1, "policy_years": -1}, {"BUYER_STATE": "FL", "BUYER_COUNTY": "HERNANDO", "fips": "12053", "year": 2006, "MME": 78727927.57445, "Population": 164398.0, "MME_per_cap": 478.8861639098408, "treatment": 1, "policy_years": -4}, {"BUYER_STATE": "FL", "BUYER_COUNTY": "HERNANDO", "fips": "12053", "year": 2007, "MME": 111241430.896115, "Population": 169891.0, "MME_per_cap": 654.7811885038938, "treatment": 1, "policy_years": -3}, {"BUYER_STATE": "FL", "BUYER_COUNTY": "HERNANDO", "fips": "12053", "year": 2008, "MME": 197158775.3677125, "Population": 172437.0, "MME_per_cap": 1143.3669999345414, "treatment": 1, "policy_years": -2}, {"BUYER_STATE": "FL", "BUYER_COUNTY": "HERNANDO", "fips": "12053", "year": 2009, "MME": 245050015.9472625, "Population": 171950.0, "MME_per_cap": 1425.1236751803576, "treatment": 1, "policy_years": -1}, {"BUYER_STATE": "FL", "BUYER_COUNTY": "HIGHLANDS", "fips": "12055", "year": 2006, "MME": 22995715.2225, "Population": 97788.0, "MME_per_cap": 235.15886634863173, "treatment": 1, "policy_years": -4}, {"BUYER_STATE": "FL", "BUYER_COUNTY": "HIGHLANDS", "fips": "12055", "year": 2007, "MME": 24466187.28794, "Population": 99023.0, "MME_per_cap": 247.07580347939367, "treatment": 1, "policy_years": -3}, {"BUYER_STATE": "FL", "BUYER_COUNTY": "HIGHLANDS", "fips": "12055", "year": 2008, "MME": 28613962.2635, "Population": 99568.0, "MME_per_cap": 287.3811090259923, "treatment": 1, "policy_years": -2}, {"BUYER_STATE": "FL", "BUYER_COUNTY": "HIGHLANDS", "fips": "12055", "year": 2009, "MME": 33721288.500675, "Population": 98956.0, "MME_per_cap": 340.77052933298637, "treatment": 1, "policy_years": -1}, {"BUYER_STATE": "FL", "BUYER_COUNTY": "HILLSBOROUGH", "fips": "12057", "year": 2006, "MME": 1027723784.987175, "Population": 1171826.0, "MME_per_cap": 877.0276346378856, "treatment": 1, "policy_years": -4}, {"BUYER_STATE": "FL", "BUYER_COUNTY": "HILLSBOROUGH", "fips": "12057", "year": 2007, "MME": 1189548966.7853, "Population": 1184686.0, "MME_per_cap": 1004.1048571396134, "treatment": 1, "policy_years": -3}, {"BUYER_STATE": "FL", "BUYER_COUNTY": "HILLSBOROUGH", "fips": "12057", "year": 2008, "MME": 1507903618.6257374, "Population": 1196773.0, "MME_per_cap": 1259.9746306323232, "treatment": 1, "policy_years": -2}, {"BUYER_STATE": "FL", "BUYER_COUNTY": "HILLSBOROUGH", "fips": "12057", "year": 2009, "MME": 2124149030.8509376, "Population": 1214050.0, "MME_per_cap": 1749.6388376516104, "treatment": 1, "policy_years": -1}, {"BUYER_STATE": "FL", "BUYER_COUNTY": "HOLMES", "fips": "12059", "year": 2006, "MME": 5115280.07, "Population": 19824.0, "MME_per_cap": 258.03470893866023, "treatment": 1, "policy_years": -4}, {"BUYER_STATE": "FL", "BUYER_COUNTY": "HOLMES", "fips": "12059", "year": 2007, "MME": 5388630.6392250005, "Population": 19991.0, "MME_per_cap": 269.5528307350808, "treatment": 1, "policy_years": -3}, {"BUYER_STATE": "FL", "BUYER_COUNTY": "HOLMES", "fips": "12059", "year": 2008, "MME": 5350438.7895875005, "Population": 20141.0, "MME_per_cap": 265.6491132310958, "treatment": 1, "policy_years": -2}, {"BUYER_STATE": "FL", "BUYER_COUNTY": "HOLMES", "fips": "12059", "year": 2009, "MME": 5461291.74045, "Population": 20147.0, "MME_per_cap": 271.07220630614984, "treatment": 1, "policy_years": -1}, {"BUYER_STATE": "FL", "BUYER_COUNTY": "INDIAN RIVER", "fips": "12061", "year": 2006, "MME": 43237351.0817625, "Population": 131463.0, "MME_per_cap": 328.8936893404418, "treatment": 1, "policy_years": -4}, {"BUYER_STATE": "FL", "BUYER_COUNTY": "INDIAN RIVER", "fips": "12061", "year": 2007, "MME": 51702138.7888875, "Population": 134564.0, "MME_per_cap": 384.21969314889196, "treatment": 1, "policy_years": -3}, {"BUYER_STATE": "FL", "BUYER_COUNTY": "INDIAN RIVER", "fips": "12061", "year": 2008, "MME": 64186802.972625, "Population": 136277.0, "MME_per_cap": 471.0024653655789, "treatment": 1, "policy_years": -2}, {"BUYER_STATE": "FL", "BUYER_COUNTY": "INDIAN RIVER", "fips": "12061", "year": 2009, "MME": 79226077.11930001, "Population": 137016.0, "MME_per_cap": 578.2250037900684, "treatment": 1, "policy_years": -1}, {"BUYER_STATE": "FL", "BUYER_COUNTY": "JACKSON", "fips": "12063", "year": 2006, "MME": 9866875.3375, "Population": 48265.0, "MME_per_cap": 204.43127188438828, "treatment": 1, "policy_years": -4}, {"BUYER_STATE": "FL", "BUYER_COUNTY": "JACKSON", "fips": "12063", "year": 2007, "MME": 11355734.5475, "Population": 48368.0, "MME_per_cap": 234.77783963570954, "treatment": 1, "policy_years": -3}, {"BUYER_STATE": "FL", "BUYER_COUNTY": "JACKSON", "fips": "12063", "year": 2008, "MME": 12130103.3215, "Population": 50272.0, "MME_per_cap": 241.28945181214195, "treatment": 1, "policy_years": -2}, {"BUYER_STATE": "FL", "BUYER_COUNTY": "JACKSON", "fips": "12063", "year": 2009, "MME": 13341586.8375, "Population": 50064.0, "MME_per_cap": 266.49062874520615, "treatment": 1, "policy_years": -1}, {"BUYER_STATE": "FL", "BUYER_COUNTY": "JEFFERSON", "fips": "12065", "year": 2006, "MME": 1465484.9205, "Population": 14461.0, "MME_per_cap": 101.34049654242445, "treatment": 1, "policy_years": -4}, {"BUYER_STATE": "FL", "BUYER_COUNTY": "JEFFERSON", "fips": "12065", "year": 2007, "MME": 1732034.337, "Population": 14383.0, "MME_per_cap": 120.4223275394563, "treatment": 1, "policy_years": -3}, {"BUYER_STATE": "FL", "BUYER_COUNTY": "JEFFERSON", "fips": "12065", "year": 2008, "MME": 2123425.9035, "Population": 14606.0, "MME_per_cap": 145.38038501300835, "treatment": 1, "policy_years": -2}, {"BUYER_STATE": "FL", "BUYER_COUNTY": "JEFFERSON", "fips": "12065", "year": 2009, "MME": 2413278.4838625, "Population": 14704.0, "MME_per_cap": 164.12394476758027, "treatment": 1, "policy_years": -1}, {"BUYER_STATE": "FL", "BUYER_COUNTY": "LAFAYETTE", "fips": "12067", "year": 2006, "MME": 1215701.375, "Population": 8341.0, "MME_per_cap": 145.7500749310634, "treatment": 1, "policy_years": -4}, {"BUYER_STATE": "FL", "BUYER_COUNTY": "LAFAYETTE", "fips": "12067", "year": 2007, "MME": 1355772.4875, "Population": 8398.0, "MME_per_cap": 161.43992468444867, "treatment": 1, "policy_years": -3}, {"BUYER_STATE": "FL", "BUYER_COUNTY": "LAFAYETTE", "fips": "12067", "year": 2008, "MME": 1361092.75, "Population": 8465.0, "MME_per_cap": 160.79063792085057, "treatment": 1, "policy_years": -2}, {"BUYER_STATE": "FL", "BUYER_COUNTY": "LAFAYETTE", "fips": "12067", "year": 2009, "MME": 1257662.175, "Population": 8435.0, "MME_per_cap": 149.1004356846473, "treatment": 1, "policy_years": -1}, {"BUYER_STATE": "FL", "BUYER_COUNTY": "LAKE", "fips": "12069", "year": 2006, "MME": 64563419.322425, "Population": 281329.0, "MME_per_cap": 229.49436184120728, "treatment": 1, "policy_years": -4}, {"BUYER_STATE": "FL", "BUYER_COUNTY": "LAKE", "fips": "12069", "year": 2007, "MME": 82180027.331575, "Population": 289909.0, "MME_per_cap": 283.46835500648484, "treatment": 1, "policy_years": -3}, {"BUYER_STATE": "FL", "BUYER_COUNTY": "LAKE", "fips": "12069", "year": 2008, "MME": 103711049.27070001, "Population": 293654.0, "MME_per_cap": 353.17431150503654, "treatment": 1, "policy_years": -2}, {"BUYER_STATE": "FL", "BUYER_COUNTY": "LAKE", "fips": "12069", "year": 2009, "MME": 140752498.570875, "Population": 295511.0, "MME_per_cap": 476.3020617536233, "treatment": 1, "policy_years": -1}, {"BUYER_STATE": "FL", "BUYER_COUNTY": "LEE", "fips": "12071", "year": 2006, "MME": 309886706.744275, "Population": 582678.0, "MME_per_cap": 531.8318294912026, "treatment": 1, "policy_years": -4}, {"BUYER_STATE": "FL", "BUYER_COUNTY": "LEE", "fips": "12071", "year": 2007, "MME": 295673263.5694625, "Population": 604716.0, "MME_per_cap": 488.9456597302907, "treatment": 1, "policy_years": -3}, {"BUYER_STATE": "FL", "BUYER_COUNTY": "LEE", "fips": "12071", "year": 2008, "MME": 340668929.5272875, "Population": 610984.0, "MME_per_cap": 557.5742237559208, "treatment": 1, "policy_years": -2}, {"BUYER_STATE": "FL", "BUYER_COUNTY": "LEE", "fips": "12071", "year": 2009, "MME": 439929930.9884625, "Population": 612297.0, "MME_per_cap": 718.491077023834, "treatment": 1, "policy_years": -1}, {"BUYER_STATE": "FL", "BUYER_COUNTY": "LEON", "fips": "12073", "year": 2006, "MME": 43067639.041725, "Population": 263076.0, "MME_per_cap": 163.70797428015098, "treatment": 1, "policy_years": -4}, {"BUYER_STATE": "FL", "BUYER_COUNTY": "LEON", "fips": "12073", "year": 2007, "MME": 47083400.8203125, "Population": 268519.0, "MME_per_cap": 175.344764505724, "treatment": 1, "policy_years": -3}, {"BUYER_STATE": "FL", "BUYER_COUNTY": "LEON", "fips": "12073", "year": 2008, "MME": 51120250.0932625, "Population": 271130.0, "MME_per_cap": 188.54516318099252, "treatment": 1, "policy_years": -2}, {"BUYER_STATE": "FL", "BUYER_COUNTY": "LEON", "fips": "12073", "year": 2009, "MME": 55928522.419125, "Population": 273263.0, "MME_per_cap": 204.66921031799035, "treatment": 1, "policy_years": -1}, {"BUYER_STATE": "FL", "BUYER_COUNTY": "LEVY", "fips": "12075", "year": 2006, "MME": 18659653.543, "Population": 39447.0, "MME_per_cap": 473.03099203995237, "treatment": 1, "policy_years": -4}, {"BUYER_STATE": "FL", "BUYER_COUNTY": "LEVY", "fips": "12075", "year": 2007, "MME": 22313800.503725, "Population": 40204.0, "MME_per_cap": 555.0144389544572, "treatment": 1, "policy_years": -3}, {"BUYER_STATE": "FL", "BUYER_COUNTY": "LEVY", "fips": "12075", "year": 2008, "MME": 28379512.6129, "Population": 40809.0, "MME_per_cap": 695.4228874243427, "treatment": 1, "policy_years": -2}, {"BUYER_STATE": "FL", "BUYER_COUNTY": "LEVY", "fips": "12075", "year": 2009, "MME": 33730549.8909, "Population": 40880.0, "MME_per_cap": 825.1112987010763, "treatment": 1, "policy_years": -1}, {"BUYER_STATE": "FL", "BUYER_COUNTY": "LIBERTY", "fips": "12077", "year": 2006, "MME": 628449.8325, "Population": 8011.0, "MME_per_cap": 78.44836256397454, "treatment": 1, "policy_years": -4}, {"BUYER_STATE": "FL", "BUYER_COUNTY": "LIBERTY", "fips": "12077", "year": 2007, "MME": 738323.0205, "Population": 8113.0, "MME_per_cap": 91.00493288549242, "treatment": 1, "policy_years": -3}, {"BUYER_STATE": "FL", "BUYER_COUNTY": "LIBERTY", "fips": "12077", "year": 2008, "MME": 771974.0625, "Population": 8323.0, "MME_per_cap": 92.75189985582122, "treatment": 1, "policy_years": -2}, {"BUYER_STATE": "FL", "BUYER_COUNTY": "LIBERTY", "fips": "12077", "year": 2009, "MME": 686362.8, "Population": 8347.0, "MME_per_cap": 82.22868096322033, "treatment": 1, "policy_years": -1}, {"BUYER_STATE": "FL", "BUYER_COUNTY": "MADISON", "fips": "12079", "year": 2006, "MME": 2315633.3313625003, "Population": 19299.0, "MME_per_cap": 119.98721857933054, "treatment": 1, "policy_years": -4}, {"BUYER_STATE": "FL", "BUYER_COUNTY": "MADISON", "fips": "12079", "year": 2007, "MME": 2632527.3742250004, "Population": 19322.0, "MME_per_cap": 136.2450768152883, "treatment": 1, "policy_years": -3}, {"BUYER_STATE": "FL", "BUYER_COUNTY": "MADISON", "fips": "12079", "year": 2008, "MME": 2793881.2853625, "Population": 19347.0, "MME_per_cap": 144.409018729648, "treatment": 1, "policy_years": -2}, {"BUYER_STATE": "FL", "BUYER_COUNTY": "MADISON", "fips": "12079", "year": 2009, "MME": 3389453.2243125, "Population": 19329.0, "MME_per_cap": 175.35584998253918, "treatment": 1, "policy_years": -1}, {"BUYER_STATE": "FL", "BUYER_COUNTY": "MANATEE", "fips": "12081", "year": 2006, "MME": 150205643.6956125, "Population": 313771.0, "MME_per_cap": 478.71104625861693, "treatment": 1, "policy_years": -4}, {"BUYER_STATE": "FL", "BUYER_COUNTY": "MANATEE", "fips": "12081", "year": 2007, "MME": 172443214.15869, "Population": 316410.0, "MME_per_cap": 544.9992546338295, "treatment": 1, "policy_years": -3}, {"BUYER_STATE": "FL", "BUYER_COUNTY": "MANATEE", "fips": "12081", "year": 2008, "MME": 196741843.14975, "Population": 318766.0, "MME_per_cap": 617.1983309065271, "treatment": 1, "policy_years": -2}, {"BUYER_STATE": "FL", "BUYER_COUNTY": "MANATEE", "fips": "12081", "year": 2009, "MME": 228282899.9302125, "Population": 320711.0, "MME_per_cap": 711.8025260443593, "treatment": 1, "policy_years": -1}, {"BUYER_STATE": "FL", "BUYER_COUNTY": "MARION", "fips": "12083", "year": 2006, "MME": 114208975.8543875, "Population": 316310.0, "MME_per_cap": 361.06659876193453, "treatment": 1, "policy_years": -4}, {"BUYER_STATE": "FL", "BUYER_COUNTY": "MARION", "fips": "12083", "year": 2007, "MME": 140167108.3894625, "Population": 325634.0, "MME_per_cap": 430.44371407611766, "treatment": 1, "policy_years": -3}, {"BUYER_STATE": "FL", "BUYER_COUNTY": "MARION", "fips": "12083", "year": 2008, "MME": 160020950.8733625, "Population": 330052.0, "MME_per_cap": 484.8355740106484, "treatment": 1, "policy_years": -2}, {"BUYER_STATE": "FL", "BUYER_COUNTY": "MARION", "fips": "12083", "year": 2009, "MME": 177998098.0790625, "Population": 330880.0, "MME_per_cap": 537.9536329758901, "treatment": 1, "policy_years": -1}, {"BUYER_STATE": "FL", "BUYER_COUNTY": "MARTIN", "fips": "12085", "year": 2006, "MME": 68573128.7873625, "Population": 141802.0, "MME_per_cap": 483.5836503530451, "treatment": 1, "policy_years": -4}, {"BUYER_STATE": "FL", "BUYER_COUNTY": "MARTIN", "fips": "12085", "year": 2007, "MME": 77097869.3673125, "Population": 143542.0, "MME_per_cap": 537.1101793712816, "treatment": 1, "policy_years": -3}, {"BUYER_STATE": "FL", "BUYER_COUNTY": "MARTIN", "fips": "12085", "year": 2008, "MME": 99157779.642725, "Population": 144369.0, "MME_per_cap": 686.8356755447846, "treatment": 1, "policy_years": -2}, {"BUYER_STATE": "FL", "BUYER_COUNTY": "MARTIN", "fips": "12085", "year": 2009, "MME": 121781256.5109, "Population": 145506.0, "MME_per_cap": 836.9500674260855, "treatment": 1, "policy_years": -1}, {"BUYER_STATE": "FL", "BUYER_COUNTY": "MIAMI-DADE", "fips": "12086", "year": 2006, "MME": 303039718.08595, "Population": 2405911.0, "MME_per_cap": 125.95632925987287, "treatment": 1, "policy_years": -4}, {"BUYER_STATE": "FL", "BUYER_COUNTY": "MIAMI-DADE", "fips": "12086", "year": 2007, "MME": 373495881.19885, "Population": 2415576.0, "MME_per_cap": 154.6198013222726, "treatment": 1, "policy_years": -3}, {"BUYER_STATE": "FL", "BUYER_COUNTY": "MIAMI-DADE", "fips": "12086", "year": 2008, "MME": 519536806.5603875, "Population": 2436062.0, "MME_per_cap": 213.26912310129524, "treatment": 1, "policy_years": -2}, {"BUYER_STATE": "FL", "BUYER_COUNTY": "MIAMI-DADE", "fips": "12086", "year": 2009, "MME": 801945146.0798625, "Population": 2463943.0, "MME_per_cap": 325.4722800323962, "treatment": 1, "policy_years": -1}, {"BUYER_STATE": "FL", "BUYER_COUNTY": "MONROE", "fips": "12087", "year": 2006, "MME": 42203180.115725, "Population": 73793.0, "MME_per_cap": 571.9130556519589, "treatment": 1, "policy_years": -4}, {"BUYER_STATE": "FL", "BUYER_COUNTY": "MONROE", "fips": "12087", "year": 2007, "MME": 46281924.684225, "Population": 72906.0, "MME_per_cap": 634.8164030974817, "treatment": 1, "policy_years": -3}, {"BUYER_STATE": "FL", "BUYER_COUNTY": "MONROE", "fips": "12087", "year": 2008, "MME": 53446096.2143625, "Population": 72730.0, "MME_per_cap": 734.8562658375155, "treatment": 1, "policy_years": -2}, {"BUYER_STATE": "FL", "BUYER_COUNTY": "MONROE", "fips": "12087", "year": 2009, "MME": 71369629.9695375, "Population": 72627.0, "MME_per_cap": 982.687292185241, "treatment": 1, "policy_years": -1}, {"BUYER_STATE": "FL", "BUYER_COUNTY": "NASSAU", "fips": "12089", "year": 2006, "MME": 26318179.4413125, "Population": 67823.0, "MME_per_cap": 388.0421013714005, "treatment": 1, "policy_years": -4}, {"BUYER_STATE": "FL", "BUYER_COUNTY": "NASSAU", "fips": "12089", "year": 2007, "MME": 30364848.846725002, "Population": 69969.0, "MME_per_cap": 433.97574421136505, "treatment": 1, "policy_years": -3}, {"BUYER_STATE": "FL", "BUYER_COUNTY": "NASSAU", "fips": "12089", "year": 2008, "MME": 38339252.757, "Population": 71557.0, "MME_per_cap": 535.7861950193552, "treatment": 1, "policy_years": -2}, {"BUYER_STATE": "FL", "BUYER_COUNTY": "NASSAU", "fips": "12089", "year": 2009, "MME": 45514900.995, "Population": 72671.0, "MME_per_cap": 626.3144995252576, "treatment": 1, "policy_years": -1}, {"BUYER_STATE": "FL", "BUYER_COUNTY": "OKALOOSA", "fips": "12091", "year": 2006, "MME": 51768878.54175, "Population": 184071.0, "MME_per_cap": 281.2440772405756, "treatment": 1, "policy_years": -4}, {"BUYER_STATE": "FL", "BUYER_COUNTY": "OKALOOSA", "fips": "12091", "year": 2007, "MME": 51948686.9043375, "Population": 182677.0, "MME_per_cap": 284.37453485845236, "treatment": 1, "policy_years": -3}, {"BUYER_STATE": "FL", "BUYER_COUNTY": "OKALOOSA", "fips": "12091", "year": 2008, "MME": 53881856.7003125, "Population": 181752.0, "MME_per_cap": 296.4581226083482, "treatment": 1, "policy_years": -2}, {"BUYER_STATE": "FL", "BUYER_COUNTY": "OKALOOSA", "fips": "12091", "year": 2009, "MME": 58085786.8360875, "Population": 181153.0, "MME_per_cap": 320.6449069907068, "treatment": 1, "policy_years": -1}, {"BUYER_STATE": "FL", "BUYER_COUNTY": "OKEECHOBEE", "fips": "12093", "year": 2006, "MME": 20628537.5353125, "Population": 39668.0, "MME_per_cap": 520.0296847663734, "treatment": 1, "policy_years": -4}, {"BUYER_STATE": "FL", "BUYER_COUNTY": "OKEECHOBEE", "fips": "12093", "year": 2007, "MME": 24923110.1409, "Population": 39840.0, "MME_per_cap": 625.5800738177711, "treatment": 1, "policy_years": -3}, {"BUYER_STATE": "FL", "BUYER_COUNTY": "OKEECHOBEE", "fips": "12093", "year": 2008, "MME": 29189020.214925, "Population": 39968.0, "MME_per_cap": 730.3097531756655, "treatment": 1, "policy_years": -2}, {"BUYER_STATE": "FL", "BUYER_COUNTY": "OKEECHOBEE", "fips": "12093", "year": 2009, "MME": 35903960.5693125, "Population": 39899.0, "MME_per_cap": 899.8711889849995, "treatment": 1, "policy_years": -1}, {"BUYER_STATE": "FL", "BUYER_COUNTY": "ORANGE", "fips": "12095", "year": 2006, "MME": 249616181.3477375, "Population": 1083429.0, "MME_per_cap": 230.39459101402815, "treatment": 1, "policy_years": -4}, {"BUYER_STATE": "FL", "BUYER_COUNTY": "ORANGE", "fips": "12095", "year": 2007, "MME": 305170616.443275, "Population": 1100663.0, "MME_per_cap": 277.2607205323291, "treatment": 1, "policy_years": -3}, {"BUYER_STATE": "FL", "BUYER_COUNTY": "ORANGE", "fips": "12095", "year": 2008, "MME": 483055087.5378, "Population": 1115525.0, "MME_per_cap": 433.02936961323144, "treatment": 1, "policy_years": -2}, {"BUYER_STATE": "FL", "BUYER_COUNTY": "ORANGE", "fips": "12095", "year": 2009, "MME": 688873467.0696375, "Population": 1131351.0, "MME_per_cap": 608.894557983895, "treatment": 1, "policy_years": -1}, {"BUYER_STATE": "FL", "BUYER_COUNTY": "OSCEOLA", "fips": "12097", "year": 2006, "MME": 50817721.9688125, "Population": 242081.0, "MME_per_cap": 209.9203240601803, "treatment": 1, "policy_years": -4}, {"BUYER_STATE": "FL", "BUYER_COUNTY": "OSCEOLA", "fips": "12097", "year": 2007, "MME": 64095232.3279875, "Population": 253722.0, "MME_per_cap": 252.61992388514793, "treatment": 1, "policy_years": -3}, {"BUYER_STATE": "FL", "BUYER_COUNTY": "OSCEOLA", "fips": "12097", "year": 2008, "MME": 93117015.4062625, "Population": 261746.0, "MME_per_cap": 355.75334639789145, "treatment": 1, "policy_years": -2}, {"BUYER_STATE": "FL", "BUYER_COUNTY": "OSCEOLA", "fips": "12097", "year": 2009, "MME": 225661792.62585, "Population": 265267.0, "MME_per_cap": 850.6968172665654, "treatment": 1, "policy_years": -1}, {"BUYER_STATE": "FL", "BUYER_COUNTY": "PALM BEACH", "fips": "12099", "year": 2006, "MME": 645319179.4898375, "Population": 1284489.0, "MME_per_cap": 502.3936985757274, "treatment": 1, "policy_years": -4}, {"BUYER_STATE": "FL", "BUYER_COUNTY": "PALM BEACH", "fips": "12099", "year": 2007, "MME": 924515014.484675, "Population": 1286586.0, "MME_per_cap": 718.580036223521, "treatment": 1, "policy_years": -3}, {"BUYER_STATE": "FL", "BUYER_COUNTY": "PALM BEACH", "fips": "12099", "year": 2008, "MME": 1334354383.1702626, "Population": 1294938.0, "MME_per_cap": 1030.4388188239611, "treatment": 1, "policy_years": -2}, {"BUYER_STATE": "FL", "BUYER_COUNTY": "PALM BEACH", "fips": "12099", "year": 2009, "MME": 1813924772.778675, "Population": 1307371.0, "MME_per_cap": 1387.4598509364787, "treatment": 1, "policy_years": -1}, {"BUYER_STATE": "FL", "BUYER_COUNTY": "PASCO", "fips": "12101", "year": 2006, "MME": 268426053.3706625, "Population": 439529.0, "MME_per_cap": 610.7129526621964, "treatment": 1, "policy_years": -4}, {"BUYER_STATE": "FL", "BUYER_COUNTY": "PASCO", "fips": "12101", "year": 2007, "MME": 356094008.8700125, "Population": 453579.0, "MME_per_cap": 785.0760482077268, "treatment": 1, "policy_years": -3}, {"BUYER_STATE": "FL", "BUYER_COUNTY": "PASCO", "fips": "12101", "year": 2008, "MME": 494709084.4496125, "Population": 461313.0, "MME_per_cap": 1072.3935472219785, "treatment": 1, "policy_years": -2}, {"BUYER_STATE": "FL", "BUYER_COUNTY": "PASCO", "fips": "12101", "year": 2009, "MME": 561319165.481925, "Population": 462607.0, "MME_per_cap": 1213.3823428567337, "treatment": 1, "policy_years": -1}, {"BUYER_STATE": "FL", "BUYER_COUNTY": "PINELLAS", "fips": "12103", "year": 2006, "MME": 607000751.4848, "Population": 924182.0, "MME_per_cap": 656.7978509479734, "treatment": 1, "policy_years": -4}, {"BUYER_STATE": "FL", "BUYER_COUNTY": "PINELLAS", "fips": "12103", "year": 2007, "MME": 636336297.667465, "Population": 918624.0, "MME_per_cap": 692.7059359079068, "treatment": 1, "policy_years": -3}, {"BUYER_STATE": "FL", "BUYER_COUNTY": "PINELLAS", "fips": "12103", "year": 2008, "MME": 933646569.568775, "Population": 916458.0, "MME_per_cap": 1018.7554362216, "treatment": 1, "policy_years": -2}, {"BUYER_STATE": "FL", "BUYER_COUNTY": "PINELLAS", "fips": "12103", "year": 2009, "MME": 1035506557.2697124, "Population": 915330.0, "MME_per_cap": 1131.2931481211283, "treatment": 1, "policy_years": -1}, {"BUYER_STATE": "FL", "BUYER_COUNTY": "POLK", "fips": "12105", "year": 2006, "MME": 178941780.43742502, "Population": 568324.0, "MME_per_cap": 314.85874331794014, "treatment": 1, "policy_years": -4}, {"BUYER_STATE": "FL", "BUYER_COUNTY": "POLK", "fips": "12105", "year": 2007, "MME": 170075524.03268752, "Population": 585982.0, "MME_per_cap": 290.2401849078769, "treatment": 1, "policy_years": -3}, {"BUYER_STATE": "FL", "BUYER_COUNTY": "POLK", "fips": "12105", "year": 2008, "MME": 171113176.12785, "Population": 594801.0, "MME_per_cap": 287.6813860902218, "treatment": 1, "policy_years": -2}, {"BUYER_STATE": "FL", "BUYER_COUNTY": "POLK", "fips": "12105", "year": 2009, "MME": 198919970.26203752, "Population": 598683.0, "MME_per_cap": 332.26260017745204, "treatment": 1, "policy_years": -1}, {"BUYER_STATE": "FL", "BUYER_COUNTY": "PUTNAM", "fips": "12107", "year": 2006, "MME": 38637502.9733875, "Population": 74663.0, "MME_per_cap": 517.4919702314065, "treatment": 1, "policy_years": -4}, {"BUYER_STATE": "FL", "BUYER_COUNTY": "PUTNAM", "fips": "12107", "year": 2007, "MME": 39640180.5800125, "Population": 75107.0, "MME_per_cap": 527.7827709802349, "treatment": 1, "policy_years": -3}, {"BUYER_STATE": "FL", "BUYER_COUNTY": "PUTNAM", "fips": "12107", "year": 2008, "MME": 45305651.0537625, "Population": 74999.0, "MME_per_cap": 604.0834018288577, "treatment": 1, "policy_years": -2}, {"BUYER_STATE": "FL", "BUYER_COUNTY": "PUTNAM", "fips": "12107", "year": 2009, "MME": 71246098.5103875, "Population": 74546.0, "MME_per_cap": 955.7333527001783, "treatment": 1, "policy_years": -1}, {"BUYER_STATE": "FL", "BUYER_COUNTY": "ST. JOHNS", "fips": "12109", "year": 2006, "MME": 43666083.525725, "Population": 168480.0, "MME_per_cap": 259.176659103306, "treatment": 1, "policy_years": -4}, {"BUYER_STATE": "FL", "BUYER_COUNTY": "ST. JOHNS", "fips": "12109", "year": 2007, "MME": 49616909.3549, "Population": 175318.0, "MME_per_cap": 283.01092503279756, "treatment": 1, "policy_years": -3}, {"BUYER_STATE": "FL", "BUYER_COUNTY": "ST. JOHNS", "fips": "12109", "year": 2008, "MME": 56641758.2135375, "Population": 181720.0, "MME_per_cap": 311.6979870874835, "treatment": 1, "policy_years": -2}, {"BUYER_STATE": "FL", "BUYER_COUNTY": "ST. JOHNS", "fips": "12109", "year": 2009, "MME": 75312165.584475, "Population": 186281.0, "MME_per_cap": 404.2933288122514, "treatment": 1, "policy_years": -1}, {"BUYER_STATE": "FL", "BUYER_COUNTY": "ST. LUCIE", "fips": "12111", "year": 2006, "MME": 95970453.4293625, "Population": 255251.0, "MME_per_cap": 375.98463249649365, "treatment": 1, "policy_years": -4}, {"BUYER_STATE": "FL", "BUYER_COUNTY": "ST. LUCIE", "fips": "12111", "year": 2007, "MME": 112422714.204925, "Population": 266860.0, "MME_per_cap": 421.27975044939296, "treatment": 1, "policy_years": -3}, {"BUYER_STATE": "FL", "BUYER_COUNTY": "ST. LUCIE", "fips": "12111", "year": 2008, "MME": 139178022.489225, "Population": 273151.0, "MME_per_cap": 509.52777946712627, "treatment": 1, "policy_years": -2}, {"BUYER_STATE": "FL", "BUYER_COUNTY": "ST. LUCIE", "fips": "12111", "year": 2009, "MME": 166843139.3083875, "Population": 274344.0, "MME_per_cap": 608.1530462061772, "treatment": 1, "policy_years": -1}, {"BUYER_STATE": "FL", "BUYER_COUNTY": "SANTA ROSA", "fips": "12113", "year": 2006, "MME": 44111678.51095, "Population": 142983.0, "MME_per_cap": 308.5099523086661, "treatment": 1, "policy_years": -4}, {"BUYER_STATE": "FL", "BUYER_COUNTY": "SANTA ROSA", "fips": "12113", "year": 2007, "MME": 51318023.23173, "Population": 146158.0, "MME_per_cap": 351.1133378380246, "treatment": 1, "policy_years": -3}, {"BUYER_STATE": "FL", "BUYER_COUNTY": "SANTA ROSA", "fips": "12113", "year": 2008, "MME": 57690950.8617125, "Population": 148538.0, "MME_per_cap": 388.3918651234869, "treatment": 1, "policy_years": -2}, {"BUYER_STATE": "FL", "BUYER_COUNTY": "SANTA ROSA", "fips": "12113", "year": 2009, "MME": 67867268.881575, "Population": 149544.0, "MME_per_cap": 453.82809662423773, "treatment": 1, "policy_years": -1}, {"BUYER_STATE": "FL", "BUYER_COUNTY": "SARASOTA", "fips": "12115", "year": 2006, "MME": 186351133.292275, "Population": 371361.0, "MME_per_cap": 501.8058797027017, "treatment": 1, "policy_years": -4}, {"BUYER_STATE": "FL", "BUYER_COUNTY": "SARASOTA", "fips": "12115", "year": 2007, "MME": 242670386.16229, "Population": 375325.0, "MME_per_cap": 646.560677179218, "treatment": 1, "policy_years": -3}, {"BUYER_STATE": "FL", "BUYER_COUNTY": "SARASOTA", "fips": "12115", "year": 2008, "MME": 324196668.0051875, "Population": 377178.0, "MME_per_cap": 859.5322845054259, "treatment": 1, "policy_years": -2}, {"BUYER_STATE": "FL", "BUYER_COUNTY": "SARASOTA", "fips": "12115", "year": 2009, "MME": 367976232.2097, "Population": 377262.0, "MME_per_cap": 975.3864216637244, "treatment": 1, "policy_years": -1}, {"BUYER_STATE": "FL", "BUYER_COUNTY": "SEMINOLE", "fips": "12117", "year": 2006, "MME": 134735668.4928125, "Population": 413218.0, "MME_per_cap": 326.06437399341877, "treatment": 1, "policy_years": -4}, {"BUYER_STATE": "FL", "BUYER_COUNTY": "SEMINOLE", "fips": "12117", "year": 2007, "MME": 185430988.6242125, "Population": 413571.0, "MME_per_cap": 448.365549383812, "treatment": 1, "policy_years": -3}, {"BUYER_STATE": "FL", "BUYER_COUNTY": "SEMINOLE", "fips": "12117", "year": 2008, "MME": 256465771.5015625, "Population": 416564.0, "MME_per_cap": 615.6695525815061, "treatment": 1, "policy_years": -2}, {"BUYER_STATE": "FL", "BUYER_COUNTY": "SEMINOLE", "fips": "12117", "year": 2009, "MME": 320779055.995875, "Population": 419788.0, "MME_per_cap": 764.1453686048077, "treatment": 1, "policy_years": -1}, {"BUYER_STATE": "FL", "BUYER_COUNTY": "SUMTER", "fips": "12119", "year": 2006, "MME": 12822867.205, "Population": 76202.0, "MME_per_cap": 168.2746805201963, "treatment": 1, "policy_years": -4}, {"BUYER_STATE": "FL", "BUYER_COUNTY": "SUMTER", "fips": "12119", "year": 2007, "MME": 16784182.853, "Population": 82101.0, "MME_per_cap": 204.433354685083, "treatment": 1, "policy_years": -3}, {"BUYER_STATE": "FL", "BUYER_COUNTY": "SUMTER", "fips": "12119", "year": 2008, "MME": 21509172.271725, "Population": 86433.0, "MME_per_cap": 248.85370485491651, "treatment": 1, "policy_years": -2}, {"BUYER_STATE": "FL", "BUYER_COUNTY": "SUMTER", "fips": "12119", "year": 2009, "MME": 30569094.9045375, "Population": 90643.0, "MME_per_cap": 337.2471664059828, "treatment": 1, "policy_years": -1}, {"BUYER_STATE": "FL", "BUYER_COUNTY": "SUWANNEE", "fips": "12121", "year": 2006, "MME": 9345596.31495, "Population": 39533.0, "MME_per_cap": 236.3998764310829, "treatment": 1, "policy_years": -4}, {"BUYER_STATE": "FL", "BUYER_COUNTY": "SUWANNEE", "fips": "12121", "year": 2007, "MME": 11324528.01785, "Population": 40309.0, "MME_per_cap": 280.9429164169292, "treatment": 1, "policy_years": -3}, {"BUYER_STATE": "FL", "BUYER_COUNTY": "SUWANNEE", "fips": "12121", "year": 2008, "MME": 12980800.460675001, "Population": 40774.0, "MME_per_cap": 318.35975034764806, "treatment": 1, "policy_years": -2}, {"BUYER_STATE": "FL", "BUYER_COUNTY": "SUWANNEE", "fips": "12121", "year": 2009, "MME": 12835535.9070375, "Population": 41263.0, "MME_per_cap": 311.0664737667523, "treatment": 1, "policy_years": -1}, {"BUYER_STATE": "FL", "BUYER_COUNTY": "TAYLOR", "fips": "12123", "year": 2006, "MME": 5544284.8075, "Population": 20793.0, "MME_per_cap": 266.64188945799066, "treatment": 1, "policy_years": -4}, {"BUYER_STATE": "FL", "BUYER_COUNTY": "TAYLOR", "fips": "12123", "year": 2007, "MME": 6762137.541362501, "Population": 21805.0, "MME_per_cap": 310.1186673406329, "treatment": 1, "policy_years": -3}, {"BUYER_STATE": "FL", "BUYER_COUNTY": "TAYLOR", "fips": "12123", "year": 2008, "MME": 8597878.620000001, "Population": 22356.0, "MME_per_cap": 384.58931025228134, "treatment": 1, "policy_years": -2}, {"BUYER_STATE": "FL", "BUYER_COUNTY": "TAYLOR", "fips": "12123", "year": 2009, "MME": 11572548.8588625, "Population": 22482.0, "MME_per_cap": 514.7473026804778, "treatment": 1, "policy_years": -1}, {"BUYER_STATE": "FL", "BUYER_COUNTY": "UNION", "fips": "12125", "year": 2006, "MME": 2453713.881, "Population": 14873.0, "MME_per_cap": 164.97773690580246, "treatment": 1, "policy_years": -4}, {"BUYER_STATE": "FL", "BUYER_COUNTY": "UNION", "fips": "12125", "year": 2007, "MME": 2777340.3794, "Population": 15419.0, "MME_per_cap": 180.12454630001946, "treatment": 1, "policy_years": -3}, {"BUYER_STATE": "FL", "BUYER_COUNTY": "UNION", "fips": "12125", "year": 2008, "MME": 3458164.69335, "Population": 15718.0, "MME_per_cap": 220.01302286232345, "treatment": 1, "policy_years": -2}, {"BUYER_STATE": "FL", "BUYER_COUNTY": "UNION", "fips": "12125", "year": 2009, "MME": 4037616.6283875, "Population": 15340.0, "MME_per_cap": 263.20838516215775, "treatment": 1, "policy_years": -1}, {"BUYER_STATE": "FL", "BUYER_COUNTY": "VOLUSIA", "fips": "12127", "year": 2006, "MME": 166518405.32765, "Population": 494748.0, "MME_per_cap": 336.5721646730255, "treatment": 1, "policy_years": -4}, {"BUYER_STATE": "FL", "BUYER_COUNTY": "VOLUSIA", "fips": "12127", "year": 2007, "MME": 195477553.01975, "Population": 498935.0, "MME_per_cap": 391.7896179256817, "treatment": 1, "policy_years": -3}, {"BUYER_STATE": "FL", "BUYER_COUNTY": "VOLUSIA", "fips": "12127", "year": 2008, "MME": 275349336.92035, "Population": 497366.0, "MME_per_cap": 553.6151182838192, "treatment": 1, "policy_years": -2}, {"BUYER_STATE": "FL", "BUYER_COUNTY": "VOLUSIA", "fips": "12127", "year": 2009, "MME": 370128379.8410625, "Population": 494688.0, "MME_per_cap": 748.2056970071287, "treatment": 1, "policy_years": -1}, {"BUYER_STATE": "FL", "BUYER_COUNTY": "WAKULLA", "fips": "12129", "year": 2006, "MME": 5464253.894, "Population": 27785.0, "MME_per_cap": 196.66200806190392, "treatment": 1, "policy_years": -4}, {"BUYER_STATE": "FL", "BUYER_COUNTY": "WAKULLA", "fips": "12129", "year": 2007, "MME": 7575903.873500001, "Population": 28588.0, "MME_per_cap": 265.0029338708549, "treatment": 1, "policy_years": -3}, {"BUYER_STATE": "FL", "BUYER_COUNTY": "WAKULLA", "fips": "12129", "year": 2008, "MME": 8114921.9535, "Population": 29183.0, "MME_per_cap": 278.0701762498715, "treatment": 1, "policy_years": -2}, {"BUYER_STATE": "FL", "BUYER_COUNTY": "WAKULLA", "fips": "12129", "year": 2009, "MME": 8481538.98, "Population": 30459.0, "MME_per_cap": 278.4575652516498, "treatment": 1, "policy_years": -1}, {"BUYER_STATE": "FL", "BUYER_COUNTY": "WALTON", "fips": "12131", "year": 2006, "MME": 22041414.055625, "Population": 51145.0, "MME_per_cap": 430.9593128482745, "treatment": 1, "policy_years": -4}, {"BUYER_STATE": "FL", "BUYER_COUNTY": "WALTON", "fips": "12131", "year": 2007, "MME": 24799001.058965, "Population": 52355.0, "MME_per_cap": 473.670156794289, "treatment": 1, "policy_years": -3}, {"BUYER_STATE": "FL", "BUYER_COUNTY": "WALTON", "fips": "12131", "year": 2008, "MME": 24625185.6823375, "Population": 53563.0, "MME_per_cap": 459.7424655515468, "treatment": 1, "policy_years": -2}, {"BUYER_STATE": "FL", "BUYER_COUNTY": "WALTON", "fips": "12131", "year": 2009, "MME": 29237208.6374625, "Population": 54534.0, "MME_per_cap": 536.128078583315, "treatment": 1, "policy_years": -1}, {"BUYER_STATE": "FL", "BUYER_COUNTY": "WASHINGTON", "fips": "12133", "year": 2006, "MME": 7659031.901000001, "Population": 22860.0, "MME_per_cap": 335.0407655730534, "treatment": 1, "policy_years": -4}, {"BUYER_STATE": "FL", "BUYER_COUNTY": "WASHINGTON", "fips": "12133", "year": 2007, "MME": 9660023.1783, "Population": 23469.0, "MME_per_cap": 411.6077880736291, "treatment": 1, "policy_years": -3}, {"BUYER_STATE": "FL", "BUYER_COUNTY": "WASHINGTON", "fips": "12133", "year": 2008, "MME": 11461812.004125, "Population": 24706.0, "MME_per_cap": 463.92827669898, "treatment": 1, "policy_years": -2}, {"BUYER_STATE": "FL", "BUYER_COUNTY": "WASHINGTON", "fips": "12133", "year": 2009, "MME": 13060632.6949875, "Population": 24693.0, "MME_per_cap": 528.9204509370064, "treatment": 1, "policy_years": -1}], "data-113aab7bb94a80666f0f75e4829506a2": [{"policy_years": -4.0, "MME_per_cap": 321.7550238126224, "ci_low": 268.37505892399923, "ci_high": 375.1349887012456}, {"policy_years": -3.97, "MME_per_cap": 324.15641905804614, "ci_low": 271.4588357299127, "ci_high": 376.85400238617956}, {"policy_years": -3.9400000000000004, "MME_per_cap": 326.5578143034699, "ci_low": 274.5375614830421, "ci_high": 378.5780671238977}, {"policy_years": -3.9100000000000006, "MME_per_cap": 328.9592095488936, "ci_low": 277.61103629864425, "ci_high": 380.307382799143}, {"policy_years": -3.880000000000001, "MME_per_cap": 331.36060479431734, "ci_low": 280.67905128088637, "ci_high": 382.0421583077483}, {"policy_years": -3.850000000000001, "MME_per_cap": 333.7620000397411, "ci_low": 283.74138814131817, "ci_high": 383.78261193816405}, {"policy_years": -3.820000000000001, "MME_per_cap": 336.1633952851648, "ci_low": 286.7978188111554, "ci_high": 385.5289717591742}, {"policy_years": -3.7900000000000014, "MME_per_cap": 338.56479053058854, "ci_low": 289.8481050492195, "ci_high": 387.2814760119576}, {"policy_years": -3.7600000000000016, "MME_per_cap": 340.9661857760123, "ci_low": 292.8919980477653, "ci_high": 389.0403735042593}, {"policy_years": -3.7300000000000018, "MME_per_cap": 343.367581021436, "ci_low": 295.9292380388699, "ci_high": 390.8059240040021}, {"policy_years": -3.700000000000002, "MME_per_cap": 345.76897626685974, "ci_low": 298.9595539045494, "ci_high": 392.57839862917007}, {"policy_years": -3.670000000000002, "MME_per_cap": 348.1703715122835, "ci_low": 301.9826627943196, "ci_high": 394.3580802302474}, {"policy_years": -3.6400000000000023, "MME_per_cap": 350.5717667577072, "ci_low": 304.99826975453067, "ci_high": 396.1452637608838}, {"policy_years": -3.6100000000000025, "MME_per_cap": 352.97316200313094, "ci_low": 308.0060673744767, "ci_high": 397.9402566317852}, {"policy_years": -3.5800000000000027, "MME_per_cap": 355.3745572485547, "ci_low": 311.00573545501493, "ci_high": 399.7433790420945}, {"policy_years": -3.550000000000003, "MME_per_cap": 357.7759524939784, "ci_low": 313.9969407062259, "ci_high": 401.5549642817309}, {"policy_years": -3.520000000000003, "MME_per_cap": 360.17734773940214, "ci_low": 316.97933648149586, "ci_high": 403.3753589973084}, {"policy_years": -3.4900000000000033, "MME_per_cap": 362.5787429848259, "ci_low": 319.95256255630335, "ci_high": 405.20492341334847}, {"policy_years": -3.4600000000000035, "MME_per_cap": 364.9801382302496, "ci_low": 322.916244960933, "ci_high": 407.04403149956624}, {"policy_years": -3.4300000000000037, "MME_per_cap": 367.38153347567334, "ci_low": 325.8699958773055, "ci_high": 408.8930710740412}, {"policy_years": -3.400000000000004, "MME_per_cap": 369.7829287210971, "ci_low": 328.8134136110828, "ci_high": 410.7524438311114}, {"policy_years": -3.370000000000004, "MME_per_cap": 372.1843239665208, "ci_low": 331.74608265115927, "ci_high": 412.6225652818824}, {"policy_years": -3.3400000000000043, "MME_per_cap": 374.58571921194454, "ci_low": 334.6675738295514, "ci_high": 414.5038645943377}, {"policy_years": -3.3100000000000045, "MME_per_cap": 376.9871144573683, "ci_low": 337.5774445955047, "ci_high": 416.3967843192319}, {"policy_years": -3.2800000000000047, "MME_per_cap": 379.388509702792, "ci_low": 340.4752394183116, "ci_high": 418.3017799872724}, {"policy_years": -3.250000000000005, "MME_per_cap": 381.78990494821574, "ci_low": 343.3604903338125, "ci_high": 420.219319562619}, {"policy_years": -3.220000000000005, "MME_per_cap": 384.1913001936395, "ci_low": 346.2327176497782, "ci_high": 422.14988273750083}, {"policy_years": -3.1900000000000053, "MME_per_cap": 386.5926954390632, "ci_low": 349.0914308252759, "ci_high": 424.09396005285055}, {"policy_years": -3.1600000000000055, "MME_per_cap": 388.99409068448693, "ci_low": 351.93612953862515, "ci_high": 426.0520518303487}, {"policy_years": -3.1300000000000057, "MME_per_cap": 391.3954859299107, "ci_low": 354.7663049575787, "ci_high": 428.0246669022427}, {"policy_years": -3.100000000000006, "MME_per_cap": 393.7968811753344, "ci_low": 357.5814412238409, "ci_high": 430.01232112682794}, {"policy_years": -3.070000000000006, "MME_per_cap": 396.19827642075813, "ci_low": 360.38101716188464, "ci_high": 432.0155356796316}, {"policy_years": -3.0400000000000063, "MME_per_cap": 398.59967166618185, "ci_low": 363.1645082191872, "ci_high": 434.0348351131765}, {"policy_years": -3.0100000000000064, "MME_per_cap": 401.0010669116056, "ci_low": 365.93138864142713, "ci_high": 436.0707451817841}, {"policy_years": -2.9800000000000066, "MME_per_cap": 403.40246215702933, "ci_low": 368.6811338818441, "ci_high": 438.12379043221455}, {"policy_years": -2.950000000000007, "MME_per_cap": 405.8038574024531, "ci_low": 371.41322323887215, "ci_high": 440.19449156603406}, {"policy_years": -2.920000000000007, "MME_per_cap": 408.2052526478768, "ci_low": 374.1271427103511, "ci_high": 442.28336258540253}, {"policy_years": -2.8900000000000072, "MME_per_cap": 410.60664789330053, "ci_low": 376.8223880462112, "ci_high": 444.3909077403899}, {"policy_years": -2.8600000000000074, "MME_per_cap": 413.00804313872425, "ci_low": 379.4984679746318, "ci_high": 446.5176183028167}, {"policy_years": -2.8300000000000076, "MME_per_cap": 415.409438384148, "ci_low": 382.15490756952056, "ci_high": 448.6639691987755}, {"policy_years": -2.800000000000008, "MME_per_cap": 417.81083362957173, "ci_low": 384.79125171997157, "ci_high": 450.8304155391719}, {"policy_years": -2.770000000000008, "MME_per_cap": 420.2122288749955, "ci_low": 387.40706865546116, "ci_high": 453.01738909452985}, {"policy_years": -2.740000000000008, "MME_per_cap": 422.6136241204192, "ci_low": 390.0019534742443, "ci_high": 455.2252947665941}, {"policy_years": -2.7100000000000084, "MME_per_cap": 425.01501936584293, "ci_low": 392.5755316171039, "ci_high": 457.454507114582}, {"policy_years": -2.6800000000000086, "MME_per_cap": 427.41641461126665, "ci_low": 395.1274622246168, "ci_high": 459.7053669979165}, {"policy_years": -2.650000000000009, "MME_per_cap": 429.8178098566904, "ci_low": 397.65744131379546, "ci_high": 461.9781783995854}, {"policy_years": -2.620000000000009, "MME_per_cap": 432.21920510211413, "ci_low": 400.16520470960376, "ci_high": 464.2732054946245}, {"policy_years": -2.590000000000009, "MME_per_cap": 434.6206003475379, "ci_low": 402.6505306686645, "ci_high": 466.5906700264113}, {"policy_years": -2.5600000000000094, "MME_per_cap": 437.0219955929616, "ci_low": 405.1132421365552, "ci_high": 468.93074904936805}, {"policy_years": -2.5300000000000096, "MME_per_cap": 439.42339083838533, "ci_low": 407.5532085864405, "ci_high": 471.29357309033014}, {"policy_years": -2.5000000000000098, "MME_per_cap": 441.82478608380904, "ci_low": 409.9703473952469, "ci_high": 473.6792247723712}, {"policy_years": -2.47000000000001, "MME_per_cap": 444.2261813292328, "ci_low": 412.3646247238927, "ci_high": 476.08773793457294}, {"policy_years": -2.44000000000001, "MME_per_cap": 446.62757657465653, "ci_low": 414.7360558798392, "ci_high": 478.51909726947383}, {"policy_years": -2.4100000000000104, "MME_per_cap": 449.0289718200803, "ci_low": 417.08470515294005, "ci_high": 480.97323848722056}, {"policy_years": -2.3800000000000106, "MME_per_cap": 451.430367065504, "ci_low": 419.41068512867776, "ci_high": 483.4500490023303}, {"policy_years": -2.3500000000000107, "MME_per_cap": 453.83176231092773, "ci_low": 421.71415549581144, "ci_high": 485.949369126044}, {"policy_years": -2.320000000000011, "MME_per_cap": 456.23315755635144, "ci_low": 423.9953213776307, "ci_high": 488.47099373507217}, {"policy_years": -2.290000000000011, "MME_per_cap": 458.6345528017752, "ci_low": 426.25443122692, "ci_high": 491.0146743766304}, {"policy_years": -2.2600000000000113, "MME_per_cap": 461.03594804719893, "ci_low": 428.4917743339287, "ci_high": 493.5801217604692}, {"policy_years": -2.2300000000000115, "MME_per_cap": 463.4373432926227, "ci_low": 430.7076780038154, "ci_high": 496.16700858143}, {"policy_years": -2.2000000000000117, "MME_per_cap": 465.8387385380464, "ci_low": 432.90250446497805, "ci_high": 498.7749726111148}, {"policy_years": -2.170000000000012, "MME_per_cap": 468.2401337834701, "ci_low": 435.0766475723481, "ci_high": 501.40361999459213}, {"policy_years": -2.140000000000012, "MME_per_cap": 470.64152902889384, "ci_low": 437.2305293701684, "ci_high": 504.05252868761926}, {"policy_years": -2.1100000000000123, "MME_per_cap": 473.0429242743176, "ci_low": 439.3645965771745, "ci_high": 506.72125197146073}, {"policy_years": -2.0800000000000125, "MME_per_cap": 475.4443195197413, "ci_low": 441.4793170537071, "ci_high": 509.40932198577553}, {"policy_years": -2.0500000000000127, "MME_per_cap": 477.8457147651651, "ci_low": 443.5751763054327, "ci_high": 512.1162532248975}, {"policy_years": -2.020000000000013, "MME_per_cap": 480.2471100105888, "ci_low": 445.6526740723772, "ci_high": 514.8415459488004}, {"policy_years": -1.990000000000013, "MME_per_cap": 482.6485052560125, "ci_low": 447.71232104527195, "ci_high": 517.584689466753}, {"policy_years": -1.9600000000000133, "MME_per_cap": 485.04990050143624, "ci_low": 449.754635744088, "ci_high": 520.3451652587845}, {"policy_years": -1.9300000000000135, "MME_per_cap": 487.45129574686, "ci_low": 451.78014158643845, "ci_high": 523.1224499072815}, {"policy_years": -1.9000000000000137, "MME_per_cap": 489.8526909922837, "ci_low": 453.78936416651027, "ci_high": 525.9160178180572}, {"policy_years": -1.8700000000000139, "MME_per_cap": 492.2540862377075, "ci_low": 455.7828287585736, "ci_high": 528.7253437168414}, {"policy_years": -1.840000000000014, "MME_per_cap": 494.6554814831312, "ci_low": 457.7610580530686, "ci_high": 531.5499049131938}, {"policy_years": -1.8100000000000143, "MME_per_cap": 497.0568767285549, "ci_low": 459.72457012790454, "ci_high": 534.3891833292053}, {"policy_years": -1.7800000000000145, "MME_per_cap": 499.45827197397864, "ci_low": 461.67387665297457, "ci_high": 537.2426672949827}, {"policy_years": -1.7500000000000147, "MME_per_cap": 501.85966721940235, "ci_low": 463.6094813220292, "ci_high": 540.1098531167755}, {"policy_years": -1.7200000000000149, "MME_per_cap": 504.2610624648261, "ci_low": 465.5318785029346, "ci_high": 542.9902464267177}, {"policy_years": -1.690000000000015, "MME_per_cap": 506.6624577102499, "ci_low": 467.44155209493795, "ci_high": 545.8833633255618}, {"policy_years": -1.6600000000000152, "MME_per_cap": 509.0638529556736, "ci_low": 469.33897457981044, "ci_high": 548.7887313315367}, {"policy_years": -1.6300000000000154, "MME_per_cap": 511.4652482010973, "ci_low": 471.2246062525676, "ci_high": 551.7058901496271}, {"policy_years": -1.6000000000000156, "MME_per_cap": 513.866643446521, "ci_low": 473.0988946168007, "ci_high": 554.6343922762413}, {"policy_years": -1.5700000000000158, "MME_per_cap": 516.2680386919448, "ci_low": 474.9622739294168, "ci_high": 557.5738034544727}, {"policy_years": -1.540000000000016, "MME_per_cap": 518.6694339373685, "ci_low": 476.81516487969446, "ci_high": 560.5237029950425}, {"policy_years": -1.5100000000000162, "MME_per_cap": 521.0708291827923, "ci_low": 478.65797438795704, "ci_high": 563.4836839776276}, {"policy_years": -1.4800000000000164, "MME_per_cap": 523.472224428216, "ci_low": 480.4910955097693, "ci_high": 566.4533533466627}, {"policy_years": -1.4500000000000166, "MME_per_cap": 525.8736196736397, "ci_low": 482.31490743233, "ci_high": 569.4323319149495}, {"policy_years": -1.4200000000000168, "MME_per_cap": 528.2750149190634, "ci_low": 484.1297755505986, "ci_high": 572.4202542875283}, {"policy_years": -1.390000000000017, "MME_per_cap": 530.6764101644872, "ci_low": 485.9360516116366, "ci_high": 575.4167687173377}, {"policy_years": -1.3600000000000172, "MME_per_cap": 533.077805409911, "ci_low": 487.73407391660595, "ci_high": 578.4215369032161}, {"policy_years": -1.3300000000000174, "MME_per_cap": 535.4792006553347, "ci_low": 489.52416757084006, "ci_high": 581.4342337398293}, {"policy_years": -1.3000000000000176, "MME_per_cap": 537.8805959007584, "ci_low": 491.30664477335466, "ci_high": 584.4545470281621}, {"policy_years": -1.2700000000000178, "MME_per_cap": 540.2819911461821, "ci_low": 493.0818051380812, "ci_high": 587.482177154283}, {"policy_years": -1.240000000000018, "MME_per_cap": 542.6833863916058, "ci_low": 494.8499360399785, "ci_high": 590.5168367432332}, {"policy_years": -1.2100000000000182, "MME_per_cap": 545.0847816370296, "ci_low": 496.61131297999395, "ci_high": 593.5582502940651}, {"policy_years": -1.1800000000000184, "MME_per_cap": 547.4861768824533, "ci_low": 498.36619996360315, "ci_high": 596.6061538013033}, {"policy_years": -1.1500000000000186, "MME_per_cap": 549.8875721278771, "ci_low": 500.1148498883526, "ci_high": 599.6602943674017}, {"policy_years": -1.1200000000000188, "MME_per_cap": 552.2889673733008, "ci_low": 501.8575049364639, "ci_high": 602.7204298101377}, {"policy_years": -1.090000000000019, "MME_per_cap": 554.6903626187245, "ci_low": 503.59439696913466, "ci_high": 605.7863282683144}, {"policy_years": -1.0600000000000191, "MME_per_cap": 557.0917578641482, "ci_low": 505.32574791968, "ci_high": 608.8577678086165}, {"policy_years": -1.0300000000000193, "MME_per_cap": 559.493153109572, "ci_low": 507.05177018312503, "ci_high": 611.9345360360189}, {"policy_years": -1.0000000000000195, "MME_per_cap": 561.8945483549958, "ci_low": 508.7726670002618, "ci_high": 615.0164297097298}, {"policy_years": -0.9700000000000197, "MME_per_cap": 564.2959436004195, "ci_low": 510.48863283454523, "ci_high": 618.1032543662938}], "data-c67d166d1bf8cb5a927f377e0e32ec7e": [{"policy_years": 0.0, "MME_per_cap": 718.9522049241468, "ci_low": 663.1514665699957, "ci_high": 774.752943278298}, {"policy_years": 0.04, "MME_per_cap": 715.1840436692445, "ci_low": 660.1248016704164, "ci_high": 770.2432856680725}, {"policy_years": 0.08, "MME_per_cap": 711.4158824143423, "ci_low": 657.0929727900436, "ci_high": 765.7387920386409}, {"policy_years": 0.12, "MME_per_cap": 707.6477211594399, "ci_low": 654.0557670752581, "ci_high": 761.2396752436217}, {"policy_years": 0.16, "MME_per_cap": 703.8795599045376, "ci_low": 651.0129614985543, "ci_high": 756.7461583105209}, {"policy_years": 0.2, "MME_per_cap": 700.1113986496354, "ci_low": 647.9643223804417, "ci_high": 752.258474918829}, {"policy_years": 0.24, "MME_per_cap": 696.343237394733, "ci_low": 644.909604898303, "ci_high": 747.7768698911631}, {"policy_years": 0.28, "MME_per_cap": 692.5750761398307, "ci_low": 641.8485525838282, "ci_high": 743.3015996958331}, {"policy_years": 0.32, "MME_per_cap": 688.8069148849285, "ci_low": 638.7808968110835, "ci_high": 738.8329329587734}, {"policy_years": 0.36, "MME_per_cap": 685.0387536300261, "ci_low": 635.7063562777914, "ci_high": 734.3711509822608}, {"policy_years": 0.4, "MME_per_cap": 681.2705923751238, "ci_low": 632.624636482984, "ci_high": 729.9165482672636}, {"policy_years": 0.44, "MME_per_cap": 677.5024311202216, "ci_low": 629.5354292048592, "ci_high": 725.469433035584}, {"policy_years": 0.48, "MME_per_cap": 673.7342698653192, "ci_low": 626.4384119834298, "ci_high": 721.0301277472087}, {"policy_years": 0.52, "MME_per_cap": 669.966108610417, "ci_low": 623.3332476134063, "ci_high": 716.5989696074276}, {"policy_years": 0.56, "MME_per_cap": 666.1979473555147, "ci_low": 620.2195836537007, "ci_high": 712.1763110573286}, {"policy_years": 0.6, "MME_per_cap": 662.4297861006123, "ci_low": 617.0970519609956, "ci_high": 707.762520240229}, {"policy_years": 0.64, "MME_per_cap": 658.6616248457101, "ci_low": 613.9652682559702, "ci_high": 703.35798143545}, {"policy_years": 0.68, "MME_per_cap": 654.8934635908078, "ci_low": 610.8238317320283, "ci_high": 698.9630954495872}, {"policy_years": 0.72, "MME_per_cap": 651.1253023359054, "ci_low": 607.6723247177189, "ci_high": 694.578279954092}, {"policy_years": 0.76, "MME_per_cap": 647.3571410810032, "ci_low": 604.510312405452, "ci_high": 690.2039697565543}, {"policy_years": 0.8, "MME_per_cap": 643.5889798261009, "ci_low": 601.3373426606066, "ci_high": 685.8406169915951}, {"policy_years": 0.84, "MME_per_cap": 639.8208185711985, "ci_low": 598.1529459266269, "ci_high": 681.4886912157701}, {"policy_years": 0.88, "MME_per_cap": 636.0526573162963, "ci_low": 594.9566352432167, "ci_high": 677.1486793893758}, {"policy_years": 0.92, "MME_per_cap": 632.284496061394, "ci_low": 591.7479063961919, "ci_high": 672.821085726596}, {"policy_years": 0.96, "MME_per_cap": 628.5163348064916, "ci_low": 588.526238218886, "ci_high": 668.5064313940973}, {"policy_years": 1.0, "MME_per_cap": 624.7481735515894, "ci_low": 585.2910930661528, "ci_high": 664.205254037026}, {"policy_years": 1.04, "MME_per_cap": 620.980012296687, "ci_low": 582.0419174828734, "ci_high": 659.9181071105007}, {"policy_years": 1.08, "MME_per_cap": 617.2118510417847, "ci_low": 578.7781430893637, "ci_high": 655.6455589942058}, {"policy_years": 1.12, "MME_per_cap": 613.4436897868825, "ci_low": 575.4991877060596, "ci_high": 651.3881918677054}, {"policy_years": 1.16, "MME_per_cap": 609.6755285319801, "ci_low": 572.2044567392188, "ci_high": 647.1466003247415}, {"policy_years": 1.2, "MME_per_cap": 605.9073672770778, "ci_low": 568.8933448479751, "ci_high": 642.9213897061805}, {"policy_years": 1.24, "MME_per_cap": 602.1392060221756, "ci_low": 565.565237910784, "ci_high": 638.7131741335671}, {"policy_years": 1.28, "MME_per_cap": 598.3710447672732, "ci_low": 562.219515305974, "ci_high": 634.5225742285725}, {"policy_years": 1.32, "MME_per_cap": 594.6028835123709, "ci_low": 558.855552516667, "ci_high": 630.3502145080748}, {"policy_years": 1.36, "MME_per_cap": 590.8347222574687, "ci_low": 555.472724064652, "ci_high": 626.1967204502854}, {"policy_years": 1.4000000000000001, "MME_per_cap": 587.0665610025663, "ci_low": 552.070406770876, "ci_high": 622.0627152342566}, {"policy_years": 1.44, "MME_per_cap": 583.298399747664, "ci_low": 548.6479833320583, "ci_high": 617.9488161632697}, {"policy_years": 1.48, "MME_per_cap": 579.5302384927618, "ci_low": 545.2048461936398, "ci_high": 613.8556307918838}, {"policy_years": 1.52, "MME_per_cap": 575.7620772378594, "ci_low": 541.7404016890347, "ci_high": 609.7837527866842}, {"policy_years": 1.56, "MME_per_cap": 571.9939159829571, "ci_low": 538.2540744042315, "ci_high": 605.7337575616828}, {"policy_years": 1.6, "MME_per_cap": 568.2257547280549, "ci_low": 534.7453117155641, "ci_high": 601.7061977405457}, {"policy_years": 1.6400000000000001, "MME_per_cap": 564.4575934731525, "ci_low": 531.2135884374335, "ci_high": 597.7015985088716}, {"policy_years": 1.68, "MME_per_cap": 560.6894322182502, "ci_low": 527.6584115064359, "ci_high": 593.7204529300645}, {"policy_years": 1.72, "MME_per_cap": 556.921270963348, "ci_low": 524.0793246193684, "ci_high": 589.7632173073275}, {"policy_years": 1.76, "MME_per_cap": 553.1531097084456, "ci_low": 520.4759127355642, "ci_high": 585.8303066813271}, {"policy_years": 1.8, "MME_per_cap": 549.3849484535433, "ci_low": 516.8478063495527, "ci_high": 581.9220905575339}, {"policy_years": 1.84, "MME_per_cap": 545.6167871986411, "ci_low": 513.1946854386812, "ci_high": 578.038888958601}, {"policy_years": 1.8800000000000001, "MME_per_cap": 541.8486259437387, "ci_low": 509.5162829924734, "ci_high": 574.1809688950041}, {"policy_years": 1.92, "MME_per_cap": 538.0804646888364, "ci_low": 505.812388036355, "ci_high": 570.3485413413177}, {"policy_years": 1.96, "MME_per_cap": 534.3123034339342, "ci_low": 502.0828480719564, "ci_high": 566.541758795912}, {"policy_years": 2.0, "MME_per_cap": 530.5441421790318, "ci_low": 498.3275708692826, "ci_high": 562.760713488781}, {"policy_years": 2.04, "MME_per_cap": 526.7759809241295, "ci_low": 494.5465255621517, "ci_high": 559.0054362861073}, {"policy_years": 2.08, "MME_per_cap": 523.0078196692273, "ci_low": 490.7397430167459, "ci_high": 555.2758963217086}, {"policy_years": 2.12, "MME_per_cap": 519.2396584143249, "ci_low": 486.90731546305955, "ci_high": 551.5720013655903}, {"policy_years": 2.16, "MME_per_cap": 515.4714971594226, "ci_low": 483.0493953994627, "ci_high": 547.8935989193825}, {"policy_years": 2.2, "MME_per_cap": 511.7033359045204, "ci_low": 479.16619380052975, "ci_high": 544.240478008511}, {"policy_years": 2.24, "MME_per_cap": 507.93517464961803, "ci_low": 475.2579776767366, "ci_high": 540.6123716224995}, {"policy_years": 2.2800000000000002, "MME_per_cap": 504.16701339471575, "ci_low": 471.3250670507361, "ci_high": 537.0089597386954}, {"policy_years": 2.32, "MME_per_cap": 500.39885213981347, "ci_low": 467.3678314279991, "ci_high": 533.4298728516279}, {"policy_years": 2.36, "MME_per_cap": 496.6306908849112, "ci_low": 463.38668584919213, "ci_high": 529.8746959206303}, {"policy_years": 2.4, "MME_per_cap": 492.8625296300089, "ci_low": 459.38208661751804, "ci_high": 526.3429726424998}, {"policy_years": 2.44, "MME_per_cap": 489.09436837510657, "ci_low": 455.3545267963808, "ci_high": 522.8342099538323}, {"policy_years": 2.48, "MME_per_cap": 485.3262071202043, "ci_low": 451.30453157137947, "ci_high": 519.3478826690291}, {"policy_years": 2.52, "MME_per_cap": 481.558045865302, "ci_low": 447.2326535661799, "ci_high": 515.8834381644241}, {"policy_years": 2.56, "MME_per_cap": 477.78988461039967, "ci_low": 443.1394681947939, "ci_high": 512.4403010260055}, {"policy_years": 2.6, "MME_per_cap": 474.02172335549733, "ci_low": 439.02556912380686, "ci_high": 509.0178775871878}, {"policy_years": 2.64, "MME_per_cap": 470.2535621005951, "ci_low": 434.89156390777833, "ci_high": 505.6155602934119}, {"policy_years": 2.68, "MME_per_cap": 466.48540084569277, "ci_low": 430.73806984998873, "ci_high": 502.2327318413968}, {"policy_years": 2.72, "MME_per_cap": 462.7172395907905, "ci_low": 426.56571012949115, "ci_high": 498.8687690520898}, {"policy_years": 2.7600000000000002, "MME_per_cap": 458.94907833588815, "ci_low": 422.3751102244965, "ci_high": 495.5230464472798}, {"policy_years": 2.8000000000000003, "MME_per_cap": 455.18091708098586, "ci_low": 418.166894651883, "ci_high": 492.1949395100887}, {"policy_years": 2.84, "MME_per_cap": 451.4127558260836, "ci_low": 413.9416840333221, "ci_high": 488.8838276188451}, {"policy_years": 2.88, "MME_per_cap": 447.6445945711813, "ci_low": 409.7000924903583, "ci_high": 485.5890966520043}, {"policy_years": 2.92, "MME_per_cap": 443.87643331627896, "ci_low": 405.4427253638578, "ci_high": 482.31014126870014}, {"policy_years": 2.96, "MME_per_cap": 440.1082720613767, "ci_low": 401.1701772475629, "ci_high": 479.0463668751905}, {"policy_years": 3.0, "MME_per_cap": 436.3401108064744, "ci_low": 396.8830303210376, "ci_high": 475.7971912919112}, {"policy_years": 3.04, "MME_per_cap": 432.57194955157206, "ci_low": 392.5818529639662, "ci_high": 472.56204613917794}, {"policy_years": 3.08, "MME_per_cap": 428.8037882966698, "ci_low": 388.26719863146747, "ci_high": 469.3403779618721}, {"policy_years": 3.12, "MME_per_cap": 425.0356270417675, "ci_low": 383.9396049686877, "ci_high": 466.1316491148473}, {"policy_years": 3.16, "MME_per_cap": 421.26746578686516, "ci_low": 379.5995931422933, "ci_high": 462.935338431437}, {"policy_years": 3.2, "MME_per_cap": 417.4993045319629, "ci_low": 375.2476673664685, "ci_high": 459.7509416974573}, {"policy_years": 3.24, "MME_per_cap": 413.7311432770606, "ci_low": 370.88431460150923, "ci_high": 456.57797195261196}, {"policy_years": 3.2800000000000002, "MME_per_cap": 409.96298202215826, "ci_low": 366.5100044039715, "ci_high": 453.415959640345}, {"policy_years": 3.3200000000000003, "MME_per_cap": 406.194820767256, "ci_low": 362.1251889084764, "ci_high": 450.26445262603556}, {"policy_years": 3.36, "MME_per_cap": 402.4266595123537, "ci_low": 357.73030292261353, "ci_high": 447.12301610209386}, {"policy_years": 3.4, "MME_per_cap": 398.6584982574514, "ci_low": 353.3257641178345, "ci_high": 443.9912323970683}, {"policy_years": 3.44, "MME_per_cap": 394.8903370025491, "ci_low": 348.911973300735, "ci_high": 440.86870070436316}, {"policy_years": 3.48, "MME_per_cap": 391.1221757476468, "ci_low": 344.4893147506359, "ci_high": 437.7550367446577}, {"policy_years": 3.52, "MME_per_cap": 387.3540144927445, "ci_low": 340.05815661085484, "ci_high": 434.6498723746342}, {"policy_years": 3.56, "MME_per_cap": 383.5858532378422, "ci_low": 335.6188513224795, "ci_high": 431.55285515320486}, {"policy_years": 3.6, "MME_per_cap": 379.8176919829399, "ci_low": 331.17173609079987, "ci_high": 428.4636478750799}, {"policy_years": 3.64, "MME_per_cap": 376.0495307280376, "ci_low": 326.7171333758027, "ci_high": 425.38192808027253}, {"policy_years": 3.68, "MME_per_cap": 372.28136947313527, "ci_low": 322.25535139929013, "ci_high": 422.3073875469804}, {"policy_years": 3.72, "MME_per_cap": 368.513208218233, "ci_low": 317.78668466223024, "ci_high": 419.23973177423574}, {"policy_years": 3.7600000000000002, "MME_per_cap": 364.74504696333065, "ci_low": 313.3114144669004, "ci_high": 416.17867945976093}, {"policy_years": 3.8000000000000003, "MME_per_cap": 360.97688570842837, "ci_low": 308.82980943923445, "ci_high": 413.1239619776223}, {"policy_years": 3.84, "MME_per_cap": 357.2087244535261, "ci_low": 304.3421260475426, "ci_high": 410.0753228595096}, {"policy_years": 3.88, "MME_per_cap": 353.4405631986238, "ci_low": 299.84860911444184, "ci_high": 407.03251728280577}, {"policy_years": 3.92, "MME_per_cap": 349.6724019437215, "ci_low": 295.34949231942267, "ci_high": 403.9953115680204}, {"policy_years": 3.96, "MME_per_cap": 345.9042406888192, "ci_low": 290.8449986899909, "ci_high": 400.96348268764746}, {"policy_years": 4.0, "MME_per_cap": 342.1360794339169, "ci_low": 286.3353410797655, "ci_high": 397.9368177880683}], "data-1cf7c250840e3c595c11ebf7ebbb5cbe": [{"a": 0}]}}